Workbook

Sheet Models
E3: Sales | G3: Purchase | I3: HR | K3: DQ
E8: currency
E10: date dim

Sheet Purchase
C3: OAON enters in contract with different vendors | H3: Vendors are different businesses who supply goods.
B5: 1 | C5: Each contract has a unique contract id | H5: PurchContracts
A7: FirstParty | B7: 2 | C7: OaOn has registered subsidiaries in different countries | H7: OaonParties | I7: OaOnPartyAddress
A9: SecondParty | B9: 3 | C9: Vendors supply goods | H9: VendTable
B11: 4 | C11: After contract is signed, PO is raised | H11: PurchaseOrder
B13: 5 | C13: Items are shipped from vendors to Oaon subsidiaries | H13: PurchItem
B15: 6 | C15: Categories | H15: PurchCategory

Sheet OaOnParties
A1: PartyId | B1: OaOnPartyName | C1: PartyAddressCode | D1: EstablishedDate | E1: PartyEmailId | F1: PartyContactNumber | G1: RecordId | H1: TaxId

Sheet OaOnPartyAddress
A1: PartyNumber | B1: Address | C1: City | D1: State | E1: Country | F1: ZipCode | G1: Region | H1: ValidFrom | I1: ValidTo | J1: RecordId

Sheet VendTable
A1: VendId | B1: VendorName | C1: LastProcessedChange_DateTime | D1: DataLakeModified_DateTime | E1: Address | F1: City | G1: State | H1: Country | I1: ZipCode | J1: Region | K1: ValidFrom | L1: ValidTo | M1: Active | N1: RecordId | O1: TaxId | P1: CurrencyCode
A2: 700001 | B2: Xgen-Ecommerce | D2: 45293 | H2: SaudiArabia | J2: MiddleEast | K2: 39448 | L2: 46002 | M2: 1 | N2: 36429234 | O2: XGE24CE | P2: SAR
A3: 700002 | B3: Destination-Ecommerce | D3: 45293 | H3: UAE | J3: MiddleEast | K3: 39449 | L3: 46009 | M3: 1 | N3: 36429234 | O3: DES89CE | P3: AED | S3: Future | T3: Shipping | W3: United States | Y3: US | Z3: United States | AA3: USD
A4: 700003 | B4: UltraSpeed-WholeSale | D4: 45293 | H4: UAE | J4: MiddleEast | K4: 39455 | L4: 46018 | M4: 1 | N4: 36429234 | O4: ULT42LE | P4: AED | S4: NewAge | T4: Products | W4: Europe | Y4: UK | Z4: Europe | AA4: GBP
A5: 700004 | B5: Buzzing-Ecommerce | D5: 45293 | H5: Qatar | J5: MiddleEast | K5: 39464 | L5: 46020 | M5: 1 | N5: 36429234 | O5: BUZ96CE | P5: QAR | S5: Xgen | T5: WholeSale | W5: MiddleEast | Y5: UAE | Z5: MiddleEast | AA5: AED
A6: 700005 | B6: USP-Shippers | D6: 45293 | H6: Kuwait | J6: MiddleEast | K6: 39465 | L6: 46024 | M6: 1 | N6: 36429234 | O6: USP59RS | P6: KWD | S6: TechBiz | T6: Ecommerce | W6: Asia | Y6: SaudiArabia | Z6: MiddleEast | AA6: SAR
A7: 700006 | B7: FMCG-WholeSale | D7: 45293 | H7: UAE | J7: MiddleEast | K7: 39475 | L7: 46025 | M7: 1 | N7: 36429234 | O7: FMC12LE | P7: AED | S7: FMCG | T7: Supplier | W7: Australia | Y7: Qatar | Z7: MiddleEast | AA7: QAR
A8: 700007 | B8: Stocker-WholeSale | D8: 45293 | H8: UK | J8: Europe | K8: 39482 | L8: 46030 | M8: 1 | N8: 36429234 | O8: STO29LE | P8: GBP | S8: AZM | T8: Movers | Y8: Kuwait | Z8: MiddleEast | AA8: KWD
A9: 700008 | B9: TechBiz-Shippers | D9: 45293 | H9: Qatar | J9: MiddleEast | K9: 39484 | L9: 46034 | M9: 1 | N9: 36429234 | O9: TEC18RS | P9: QAR | S9: Buzzing | T9: Shippers | Y9: Egypt | Z9: MiddleEast | AA9: EGP
A10: 700009 | B10: Rapid-WholeSale | D10: 45293 | H10: India | J10: Asia | K10: 39488 | L10: 46039 | M10: 1 | N10: 36429234 | O10: RAP82LE | P10: INR | S10: Destination | Y10: Turkiye | Z10: MiddleEast | AA10: TRP
A11: 700010 | B11: Stocker-Products | D11: 45293 | H11: SaudiArabia | J11: MiddleEast | K11: 39491 | L11: 46040 | M11: 1 | N11: 36429234 | O11: STO92TS | P11: SAR | S11: Stocker | Y11: India | Z11: Asia | AA11: INR
A12: 700011 | B12: Rapid-Movers | D12: 45293 | H12: US | J12: United States | K12: 39496 | L12: 46046 | M12: 1 | N12: 36429234 | O12: RAP26RS | P12: USD | S12: Innovative | Y12: Pakistan | Z12: Asia | AA12: PKR
A13: 700012 | B13: AZM-Shipping | D13: 45293 | H13: UAE | J13: MiddleEast | K13: 39503 | L13: 46047 | M13: 1 | N13: 36429234 | O13: AZM11NG | P13: AED | S13: ShopAtUs | Y13: Australia | Z13: Australia | AA13: AUD
A14: 700013 | B14: Innovative-Movers | D14: 45293 | H14: Pakistan | J14: Asia | K14: 39506 | L14: 46050 | M14: 1 | N14: 36429234 | O14: INN95RS | P14: PKR | S14: Etail
A15: 700014 | B15: Etail-Shippers | D15: 45293 | H15: US | J15: United States | K15: 39510 | L15: 46051 | M15: 1 | N15: 36429234 | O15: ETA12RS | P15: USD | S15: FastDelivery
A16: 700015 | B16: AZM-Supplier | D16: 45293 | H16: Turkiye | J16: MiddleEast | K16: 39512 | L16: 46056 | M16: 1 | N16: 36429234 | O16: AZM21ER | P16: TRP | S16: Rapid
A17: 700016 | B17: Buzzing-Supplier | D17: 45293 | H17: Pakistan | J17: Asia | K17: 39519 | L17: 46061 | M17: 1 | N17: 36429234 | O17: BUZ38ER | P17: PKR | S17: UltraSpeed
A18: 700017 | B18: FastDelivery-Products | D18: 45293 | H18: UK | J18: Europe | K18: 39527 | L18: 46065 | M18: 1 | N18: 36429234 | O18: FAS59TS | P18: GBP | S18: USP
A19: 700018 | B19: UltraSpeed-Supplier | D19: 45293 | H19: Turkiye | J19: MiddleEast | K19: 39532 | L19: 46074 | M19: 1 | N19: 36429234 | O19: ULT27ER | P19: TRP
A20: 700019 | B20: Future-Shipping | D20: 45293 | H20: India | J20: Asia | K20: 39537 | L20: 46083 | M20: 1 | N20: 36429234 | O20: FUT61NG | P20: INR
A21: 700020 | B21: USP-WholeSale | D21: 45293 | H21: US | J21: United States | K21: 39547 | L21: 46088 | M21: 1 | N21: 36429234 | O21: USP55LE | P21: USD
A22: 700021 | B22: Etail-Movers | D22: 45293 | H22: Qatar | J22: MiddleEast | K22: 39553 | L22: 46092 | M22: 1 | N22: 36429234 | O22: ETA77RS | P22: QAR
A23: 700022 | B23: USP-Products | D23: 45293 | H23: Pakistan | J23: Asia | K23: 39554 | L23: 46100 | M23: 1 | N23: 36429234 | O23: USP32TS | P23: PKR
A24: 700023 | B24: TechBiz-Ecommerce | D24: 45293 | H24: Pakistan | J24: Asia | K24: 39559 | L24: 46105 | M24: 1 | N24: 36429234 | O24: TEC45CE | P24: PKR
A25: 700001 | B25: Future-Supplier | D25: 45293 | H25: Kuwait | J25: MiddleEast | K25: 39566 | L25: 46110 | M25: 1 | N25: 36429234 | O25: FUT38ER | P25: KWD
A26: 700002 | B26: ShopAtUs-Ecommerce | D26: 45293 | H26: SaudiArabia | J26: MiddleEast | K26: 39568 | L26: 46118 | M26: 1 | N26: 36429234 | O26: SHO49CE | P26: SAR
A27: 700003 | B27: NewAge-Shipping | D27: 45293 | H27: SaudiArabia | J27: MiddleEast | K27: 39571 | L27: 46126 | M27: 1 | N27: 36429234 | O27: NEW41NG | P27: SAR
A28: 700004 | B28: Etail-Shipping | D28: 45293 | H28: Turkiye | J28: MiddleEast | K28: 39573 | L28: 46131 | M28: 1 | N28: 36429234 | O28: ETA68NG | P28: TRP
A29: 700005 | B29: AZM-Ecommerce | D29: 45293 | H29: US | J29: United States | K29: 39574 | L29: 46141 | M29: 1 | N29: 36429234 | O29: AZM77CE | P29: USD
A30: 700006 | B30: Buzzing-WholeSale | D30: 45293 | H30: Pakistan | J30: Asia | K30: 39580 | L30: 46143 | M30: 1 | N30: 36429234 | O30: BUZ14LE | P30: PKR
... A109: 700016 | B109: Stocker-Movers | D109: 45293 | H109: SaudiArabia | J109: MiddleEast | K109: 40058 | L109: 46558 | M109: 1 | N109: 36429234 | O109: STO66RS | P109: SAR

Sheet Sheet8

Sheet PurchContracts
A1: OaOnContractId | B1: LastProcessedChange_DateTime | C1: DataLakeModified_DateTime | D1: FirstParty | E1: SecondParty | F1: ValidFrom | G1: ValidTo | H1: IsActive | I1: RecordId
A2: 97400000001 | C2: 45293 | D2: 10001 | E2: 700001 | F2: 44927 | G2: 46022 | H2: 1 | I2: 65417281
A3: 97400000002 | C3: 45293 | D3: 10002 | E3: 700002 | F3: 44928 | G3: 46023 | H3: 1 | I3: 65417282
A4: 97400000003 | C4: 45293 | D4: 10003 | E4: 700003 | F4: 44929 | G4: 46024 | H4: 1 | I4: 65417283
A5: 97400000004 | C5: 45293 | D5: 10004 | E5: 700004 | F5: 44930 | G5: 46025 | H5: 1 | I5: 65417284
A6: 97400000005 | C6: 45293 | D6: 10005 | E6: 700005 | F6: 44931 | G6: 46026 | H6: 1 | I6: 65417285
A7: 97400000006 | C7: 45293 | D7: 10006 | E7: 700006 | F7: 44932 | G7: 46027 | H7: 1 | I7: 65417286
A8: 97400000007 | C8: 45293 | D8: 10007 | E8: 700007 | F8: 44933 | G8: 46028 | H8: 1 | I8: 65417287
A9: 97400000008 | C9: 45293 | D9: 10008 | E9: 700008 | F9: 44934 | G9: 46029 | H9: 1 | I9: 65417288
A10: 97400000009 | C10: 45293 | D10: 10009 | E10: 700009 | F10: 44935 | G10: 46030 | H10: 1 | I10: 65417289
A11: 97400000010 | C11: 45293 | D11: 10010 | E11: 700010 | F11: 44936 | G11: 46031 | H11: 1 | I11: 65417290
A12: 97400000011 | C12: 45293 | D12: 10011 | E12: 700011 | F12: 44937 | G12: 46032 | H12: 1 | I12: 65417291
A13: 97400000012 | C13: 45293 | D13: 10012 | E13: 700012 | F13: 44938 | G13: 46033 | H13: 1 | I13: 65417292
... A24: 97400000023 | C24: 45293 | D24: 10022 | E24: 700023 | F24: 44949 | G24: 46044 | H24: 1 | I24: 65417303

Sheet PurchaseOrder
A1: PoNumber | B1: LineItem | C1: VendId | D1: LastProcessedChange_DateTime | E1: DataLakeModified_DateTime | F1: Qty | G1: PurchasePrice | H1: TotalOrder | I1: ExchangeRate | J1: costcenter | K1: Itemkey | L1: currencycode | M1: OrderDate | N1: ShipDate | O1: DeliveredDate | P1: TrackingNumber | Q1: batchid | R1: CreatedBy | S1: RecordId | T1: CategoryId
A2: 952000001 | B2: 1 | C2: =IF(A2=A1,PurchaseOrder!C1,INDEX(VendTable!$A$2:$A$109,RANDBETWEEN(1,23))) -> 700023 | E2: 2024-01-02T14:16:06.9086921Z | F2: 15543 | G2: 9013.7959 | H2: 1.4010143e+08 | I2: 1.4881644 | J2: 76860 | K2: 76891213535 | L2: US | M2: 44601.595 | N2: 44602.189 | O2: 44608.784 | P2: 10397261234 | Q2: 981856 | S2: 25612344 | T2: 500 | U2: 0.59452441 | W2: 76852 | Z2: 76852
A3: 952000001 | B3: 2 | C3: =IF(A3=A2,PurchaseOrder!C2,INDEX(VendTable!$A$2:$A$109,RANDBETWEEN(1,23))) -> 700023 | E3: 2024-01-02T14:16:06.9086921Z | F3: 28211 | G3: 5278.0982 | H3: 1.4890043e+08 | I3: 1.8813002 | J3: 76861 | K3: 76891213636 | L3: US | M3: 44933.595 | N3: 44935.189 | O3: 44942.784 | P3: 10397261234 | Q3: 981946 | S3: 25612434 | T3: 1000 | W3: 76853 | Z3: 76853
A4: 952000001 | B4: 3 | C4: =IF(A4=A3,PurchaseOrder!C3,INDEX(VendTable!$A$2:$A$109,RANDBETWEEN(1,23))) -> 700023 | E4: 2024-01-02T14:16:06.9086921Z | F4: 6594 | G4: 7226.5803 | H4: 47652070 | I4: 1.6100954 | J4: 76861 | K4: 76891213465 | L4: US | M4: 45524.595 | N4: 45525.189 | O4: 45527.784 | P4: 10397261234 | Q4: 981991 | S4: 25612479 | T4: 500 | W4: 76854 | Z4: 76854
A5: 952000002 | B5: 1 | C5: =IF(A5=A4,PurchaseOrder!C4,INDEX(VendTable!$A$2:$A$109,RANDBETWEEN(1,23))) -> 700004 | E5: 2024-01-02T14:16:06.9086921Z | F5: 27796 | G5: 6047.5037 | H5: 1.6809641e+08 | I5: 1.1377751 | J5: 76854 | K5: 76891213212 | L5: US | M5: 45282.595 | N5: 45283.189 | O5: 45293.784 | P5: 10397261234 | Q5: 981890 | S5: 25612378 | T5: 900 | W5: 76855 | Z5: 76855
A6: 952000003 | B6: 1 | C6: =IF(A6=A5,PurchaseOrder!C5,INDEX(VendTable!$A$2:$A$109,RANDBETWEEN(1,23))) -> 700007 | E6: 2024-01-02T14:16:06.9086921Z | F6: 22504 | G6: 7871.7995 | H6: 1.7714698e+08 | I6: 1.9402531 | J6: 76853 | K6: 76891213318 | L6: US | M6: 44715.595 | N6: 44719.189 | O6: 44727.784 | P6: 10397261234 | Q6: 982001 | S6: 25612489 | T6: 900 | W6: 76856 | Z6: 76856
A7: 952000004 | B7: 1 | C7: =IF(A7=A6,PurchaseOrder!C6,INDEX(VendTable!$A$2:$A$109,RANDBETWEEN(1,23))) -> 700006 | E7: 2024-01-02T14:16:06.9086921Z | F7: 44236 | G7: 434.51764 | H7: 19221322 | I7: 1.6510293 | J7: 76862 | K7: 76891213154 | L7: US | M7: 44983.595 | N7: 44986.189 | O7: 44986.784 | P7: 10397261234 | Q7: 982010 | S7: 25612498 | T7: 900 | W7: 76857 | Z7: 76857
A8: 952000005 | B8: 1 | C8: =IF(A8=A7,PurchaseOrder!C7,INDEX(VendTable!$A$2:$A$109,RANDBETWEEN(1,23))) -> 700019 | E8: 2024-01-02T14:16:06.9086921Z | F8: 41200 | G8: 7671.9345 | H8: 3.160837e+08 | I8: 1.8501127 | J8: 76861 | K8: 76891213531 | L8: US | M8: 45193.595 | N8: 45195.189 | O8: 45205.784 | P8: 10397261234 | Q8: 981903 | S8: 25612391 | T8: 400 | W8: 76858 | Z8: 76858
A9: 952000005 | B9: 2 | C9: =IF(A9=A8,PurchaseOrder!C8,INDEX(VendTable!$A$2:$A$109,RANDBETWEEN(1,23))) -> 700019 | E9: 2024-01-02T14:16:06.9086921Z | F9: 27335 | G9: 456.46039 | H9: 12477345 | I9: 1.2223787 | J9: 76860 | K9: 76891213463 | L9: US | M9: 44916.595 | N9: 44920.189 | O9: 44927.784 | P9: 10397261234 | Q9: 981923 | S9: 25612411 | T9: 1000 | W9: 76859 | Z9: 76859
A10: 952000006 | B10: 1 | C10: =IF(A10=A9,PurchaseOrder!C9,INDEX(VendTable!$A$2:$A$109,RANDBETWEEN(1,23))) -> 700012 | E10: 2024-01-02T14:16:06.9086921Z | F10: 6500 | G10: 5988.5573 | H10: 38925622 | I10: 1.2875963 | J10: 76866 | K10: 76891213364 | L10: US | M10: 44860.595 | N10: 44863.189 | O10: 44863.784 | P10: 10397261234 | Q10: 981885 | S10: 25612373 | T10: 100 | W10: 76860 | Z10: 76860
A11: 952000006 | B11: 2 | C11: =IF(A11=A10,PurchaseOrder!C10,INDEX(VendTable!$A$2:$A$109,RANDBETWEEN(1,23))) -> 700012 | E11: 2024-01-02T14:16:06.9086921Z | F11: 39988 | G11: 7141.7755 | H11: 2.8558532e+08 | I11: 1.6454282 | J11: 76864 | K11: 76891213207 | L11: US | M11: 45302.595 | N11: 45304.189 | O11: 45313.784 | P11: 10397261234 | Q11: 981937 | S11: 25612425 | T11: 1000 | W11: 76861 | Z11: 76861
A12: 952000006 | B12: 3 | C12: =IF(A12=A11,PurchaseOrder!C11,INDEX(VendTable!$A$2:$A$109,RANDBETWEEN(1,23))) -> 700012 | E12: 2024-01-02T14:16:06.9086921Z | F12: 6090 | G12: 9901.8673 | H12: 60302372 | I12: 1.2702625 | J12: 76870 | K12: 76891213372 | L12: US | M12: 44900.595 | N12: 44903.189 | O12: 44906.784 | P12: 10397261234 | Q12: 981947 | S12: 25612435 | T12: 500 | W12: 76862 | Z12: 76862
A13: 952000006 | B13: 4 | C13: =IF(A13=A12,PurchaseOrder!C12,INDEX(VendTable!$A$2:$A$109,RANDBETWEEN(1,23))) -> 700012 | E13: 2024-01-02T14:16:06.9086921Z | F13: 43751 | G13: 8471.4389 | H13: 3.7063393e+08 | I13: 1.1615616 | J13: 76865 | K13: 76891213508 | L13: US | M13: 44643.595 | N13: 44646.189 | O13: 44655.784 | P13: 10397261234 | Q13: 981951 | S13: 25612439 | T13: 1000 | W13: 76863 | Z13: 76863
A14: 952000006 | B14: 5 | C14: =IF(A14=A13,PurchaseOrder!C13,INDEX(VendTable!$A$2:$A$109,RANDBETWEEN(1,23))) -> 700012 | E14: 2024-01-02T14:16:06.9086921Z | F14: 42667 | G14: 1104.5531 | H14: 47127966 | I14: 1.7833928 | J14: 76868 | K14: 76891213481 | L14: US | M14: 45037.595 | N14: 45041.189 | O14: 45049.784 | P14: 10397261234 | Q14: 982000 | S14: 25612488 | T14: 1000 | W14: 76864 | Z14: 76864
... A24: 952000014 | B24: 4 | C24: =IF(A24=A23,PurchaseOrder!C23,INDEX(VendTable!$A$2:$A$109,RANDBETWEEN(1,23))) -> 700021 | E24: 2024-01-02T14:16:06.9086921Z | F24: 12901 | G24: 3606.1603 | H24: 46523074 | I24: 1.3257147 | J24: 76862 | K24: 76891213518 | L24: US | M24: 45588.595 | N24: 45589.189 | O24: 45599.784 | P24: 10397261234 | Q24: 982025 | S24: 25612513 | T24: 300 | W24: 76874 | Z24: 76874
A25: 952000014 | B25: 5 | C25: =IF(A25=A24,PurchaseOrder!C24,INDEX(VendTable!$A$2:$A$109,RANDBETWEEN(1,23))) -> 700021 | E25: 2024-01-02T14:16:06.9086921Z | F25: 31557 | G25: 9218.6561 | H25: 2.9091313e+08 | I25: 1.7027658 | J25: 76860 | K25: 76891213157 | L25: US | M25: 45390.595 | N25: 45392.189 | O25: 45394.784 | P25: 10397261234 | Q25: 982026 | S25: 25612514 | T25: 400
A26: 952000016 | B26: 1 | C26: =IF(A26=A25,PurchaseOrder!C25,INDEX(VendTable!$A$2:$A$109,RANDBETWEEN(1,23))) -> 700009 | E26: 2024-01-02T14:16:06.9086921Z | F26: 45398 | G26: 8298.2466 | H26: 3.767238e+08 | I26: 1.2596188 | J26: 76852 | K26: 76891213515 | L26: US | M26: 44750.595 | N26: 44751.189 | O26: 44760.784 | P26: 10397261234 | Q26: 981988 | S26: 25612476 | T26: 600
A27: 952000016 | B27: 2 | C27: =IF(A27=A26,PurchaseOrder!C26,INDEX(VendTable!$A$2:$A$109,RANDBETWEEN(1,23))) -> 700009 | E27: 2024-01-02T14:16:06.9086921Z | F27: 35291 | G27: 722.47856 | H27: 25496991 | I27: 1.0348933 | J27: 76860 | K27: 76891213241 | L27: US | M27: 44693.595 | N27: 44694.189 | O27: 44694.784 | P27: 10397261234 | Q27: 981997 | S27: 25612485 | T27: 700
A28: 952000017 | B28: 1 | C28: =IF(A28=A27,PurchaseOrder!C27,INDEX(VendTable!$A$2:$A$109,RANDBETWEEN(1,23))) -> 700015 | E28: 2024-01-02T14:16:06.9086921Z | F28: 16631 | G28: 8262.4795 | H28: 1.374133e+08 | I28: 1.0519482 | J28: 76871 | K28: 76891213352 | L28: US | M28: 44659.595 | N28: 44663.189 | O28: 44664.784 | P28: 10397261234 | Q28: 981892 | S28: 25612380 | T28: 500
A29: 952000017 | B29: 2 | C29: =IF(A29=A28,PurchaseOrder!C28,INDEX(VendTable!$A$2:$A$109,RANDBETWEEN(1,23))) -> 700015 | E29: 2024-01-02T14:16:06.9086921Z | F29: 11319 | G29: 4691.9138 | H29: 53107772 | I29: 1.4568726 | J29: 76863 | K29: 76891213324 | L29: US | M29: 44668.595 | N29: 44670.189 | O29: 44676.784 | P29: 10397261234 | Q29: 981959 | S29: 25612447 | T29: 100
A30: 952000019 | B30: 1 | C30: =IF(A30=A29,PurchaseOrder!C29,INDEX(VendTable!$A$2:$A$109,RANDBETWEEN(1,23))) -> 700011 | E30: 2024-01-02T14:16:06.9086921Z | F30: 42604 | G30: 6289.9679 | H30: 2.6797779e+08 | I30: 1.0675251 | J30: 76855 | K30: 76891213464 | L30: US | M30: 44841.595 | N30: 44844.189 | O30: 44852.784 | P30: 10397261215 | Q30: 981835 | S30: 25612323 | T30: 200
A31: 952000020 | B31: 1 | C31: =IF(A31=A30,PurchaseOrder!C30,INDEX(VendTable!$A$2:$A$109,RANDBETWEEN(1,23))) -> 700014 | E31: 2024-01-02T14:16:06.9086921Z | F31: 5485 | G31: 5297.7343 | H31: 29058073 | I31: 1.8963767 | J31: 76867 | K31: 76891213450 | L31: US | M31: 45301.595 | N31: 45302.189 | O31: 45308.784 | P31: 10397261234 | Q31: 981927 | S31: 25612415 | T31: 800
A32: 952000020 | B32: 2 | C32: =IF(A32=A31,PurchaseOrder!C31,INDEX(VendTable!$A$2:$A$109,RANDBETWEEN(1,23))) -> 700014 | E32: 2024-01-02T14:16:06.9086921Z | F32: 19524 | G32: 8918.4092 | H32: 1.7412302e+08 | I32: 1.3290569 | J32: 76865 | K32: 76891213415 | L32: US | M32: 45255.595 | N32: 45258.189 | O32: 45263.784 | P32: 10397261234 | Q32: 982013 | S32: 25612501 | T32: 700
A33: 952000021 | B33: 1 | C33: =IF(A33=A32,PurchaseOrder!C32,INDEX(VendTable!$A$2:$A$109,RANDBETWEEN(1,23))) -> 700017 | E33: 2024-01-02T14:16:06.9086921Z | F33: 40304 | G33: 1470.2265 | H33: 59256008 | I33: 1.7222778 | J33: 76866 | K33: 76891213194 | L33: US | M33: 44785.595 | N33: 44789.189 | O33: 44793.784 | P33: 10397261234 | Q33: 981887 | S33: 25612375 | T33: 400
A34: 952000021 | B34: 2 | C34: =IF(A34=A33,PurchaseOrder!C33,INDEX(VendTable!$A$2:$A$109,RANDBETWEEN(1,23))) -> 700017 | E34: 2024-01-02T14:16:06.9086921Z | F34: 24533 | G34: 5173.8412 | H34: 1.2692985e+08 | I34: 1.6626016 | J34: 76855 | K34: 76891213487 | L34: US | M34: 44653.595 | N34: 44654.189 | O34: 44656.784 | P34: 10397261234 | Q34: 981931 | S34: 25612419 | T34: 1000
A35: 952000023 | B35: 1 | C35: =IF(A35=A34,PurchaseOrder!C34,INDEX(VendTable!$A$2:$A$109,RANDBETWEEN(1,23))) -> 700015 | E35: 2024-01-02T14:16:06.9086921Z | F35: 16463 | G35: 7427.1598 | H35: 1.2227333e+08 | I35: 1.9967414 | J35: 76856 | K35: 76891213219 | L35: US | M35: 45370.595 | N35: 45374.189 | O35: 45375.784 | P35: 10397261234 | Q35: 981868 | S35: 25612356 | T35: 400
A36: 952000023 | B36: 2 | C36: =IF(A36=A35,PurchaseOrder!C35,INDEX(VendTable!$A$2:$A$109,RANDBETWEEN(1,23))) -> 700015 | E36: 2024-01-02T14:16:06.9086921Z | F36: 22698 | G36: 1875.5988 | H36: 42572341 | I36: 1.6267861 | J36: 76862 | K36: 76891213612 | L36: US | M36: 45340.595 | N36: 45344.189 | O36: 45354.784 | P36: 10397261234 | Q36: 981902 | S36: 25612390 | T36: 100
... A125: 952000082 | B125: 3 | C125: =IF(A125=A124,PurchaseOrder!C124,INDEX(VendTable!$A$2:$A$109,RANDBETWEEN(1,23))) -> 700007 | E125: 2024-01-02T14:16:06.9086921Z | F125: 7537 | G125: 2139.6017 | H125: 16126178 | I125: 1.4113029 | J125: 76870 | K125: 76891213236 | L125: US | M125: 45409.595 | N125: 45412.189 | O125: 45417.784 | P125: 10397261234 | Q125: 981970 | S125: 25612458 | T125: 900
A126: 952000083 | B126: 1 | C126: =IF(A126=A125,PurchaseOrder!C125,INDEX(VendTable!$A$2:$A$109,RANDBETWEEN(1,23))) -> 700018 | E126: 2024-01-02T14:16:06.9086921Z | F126: =RANDBETWEEN(5000,50000) -> 48179 | G126: =VLOOKUP(K126,PurchItem!$A$2:$H$508,8,0) -> 7411.6309 | H126: =F126*G126 -> 3.5708496e+08 | I126: =1+RAND() -> 1.6536154 | J126: =INDEX($W$2:$W$24,RANDBETWEEN(1,20)) -> 76867 | K126: =INDEX(PurchItem!$A$2:$A$508,RANDBETWEEN(1,500)) -> 76891213350 | L126: US | M126: =RANDBETWEEN(DATE(2022,1,1),TODAY()-30)+$U$2 -> 45256.595 | N126: =M126+RANDBETWEEN(0,3)+$U$2 -> 45259.189 | O126: =N126+RANDBETWEEN(0,10)+$U$2 -> 45264.784 | P126: 10397261213 | Q126: 981833 | S126: 25612321 | T126: 700
A127: 952000083 | B127: 2 | C127: =IF(A127=A126,PurchaseOrder!C126,INDEX(VendTable!$A$2:$A$109,RANDBETWEEN(1,23))) -> 700018 | E127: 2024-01-02T14:16:06.9086921Z | F127: 8394 | G127: 9818.5215 | H127: 82416669 | I127: 1.220076 | J127: 76862 | K127: 76891213491 | L127: US | M127: 44774.595 | N127: 44776.189 | O127: 44786.784 | P127: 10397261234 | Q127: 982012 | S127: 25612500 | T127: 400
A128: 952000084 | B128: 1 | C128: =IF(A128=A127,PurchaseOrder!C127,INDEX(VendTable!$A$2:$A$109,RANDBETWEEN(1,23))) -> 700017 | E128: 2024-01-02T14:16:06.9086921Z | F128: 38472 | G128: 7671.9345 | H128: 2.9515466e+08 | I128: 1.4640816 | J128: 76870 | K128: 76891213531 | L128: US | M128: 45569.595 | N128: 45571.189 | O128: 45572.784 | P128: 10397261234 | Q128: 981983 | S128: 25612471 | T128: 400
A129: 952000084 | B129: 2 | C129: =IF(A129=A128,PurchaseOrder!C128,INDEX(VendTable!$A$2:$A$109,RANDBETWEEN(1,23))) -> 700017 | E129: 2024-01-02T14:16:06.9086921Z | F129: 41588 | G129: 5678.9303 | H129: 2.3617535e+08 | I129: 1.3022958 | J129: 76857 | K129: 76891213258 | L129: US | M129: 44605.595 | N129: 44609.189 | O129: 44612.784 | P129: 10397261234 | Q129: 982017 | S129: 25612505 | T129: 200
A130: 952000085 | B130: 1 | C130: =IF(A130=A129,PurchaseOrder!C129,INDEX(VendTable!$A$2:$A$109,RANDBETWEEN(1,23))) -> 700006 | E130: 2024-01-02T14:16:06.9086921Z | F130: 23778 | G130: 9568.6503 | H130: 2.2752337e+08 | I130: 1.7953566 | J130: 76861 | K130: 76891213548 | L130: US | M130: 45491.595 | N130: 45493.189 | O130: 45496.784 | P130: 10397261234 | Q130: 982014 | S130: 25612502 | T130: 500
A131: 952000087 | B131: 1 | C131: =IF(A131=A130,PurchaseOrder!C130,INDEX(VendTable!$A$2:$A$109,RANDBETWEEN(1,23))) -> 700021 | E131: 2024-01-02T14:16:06.9086921Z | F131: 45620 | G131: 2742.8844 | H131: 1.2513039e+08 | I131: 1.7942564 | J131: 76861 | K131: 76891213522 | L131: US | M131: 45521.595 | N131: 45523.189 | O131: 45531.784 | P131: 10397261225 | Q131: 981845 | S131: 25612333 | T131: 300
A132: 952000087 | B132: 2 | C132: =IF(A132=A131,PurchaseOrder!C131,INDEX(VendTable!$A$2:$A$109,RANDBETWEEN(1,23))) -> 700021 | E132: 2024-01-02T14:16:06.9086921Z | F132: 22929 | G132: 175.54473 | H132: 4025065.2 | I132: 1.9305963 | J132: 76856 | K132: 76891213300 | L132: US | M132: 45590.595 | N132: 45593.189 | O132: 45600.784 | P132: 10397261234 | Q132: 981928 | S132: 25612416 | T132: 100
A133: 952000087 | B133: 3 | C133: =IF(A133=A132,PurchaseOrder!C132,INDEX(VendTable!$A$2:$A$109,RANDBETWEEN(1,23))) -> 700021 | E133: 2024-01-02T14:16:06.9086921Z | F133: 16765 | G133: 8555.7858 | H133: 1.4343775e+08 | I133: 1.3135378 | J133: 76855 | K133: 76891213149 | L133: US | M133: 45408.595 | N133: 45411.189 | O133: 45416.784 | P133: 10397261234 | Q133: 982015 | S133: 25612503 | T133: 400
A134: 952000087 | B134: 4 | C134: =IF(A134=A133,PurchaseOrder!C133,INDEX(VendTable!$A$2:$A$109,RANDBETWEEN(1,23))) -> 700021 | E134: 2024-01-02T14:16:06.9086921Z | F134: 8996 | G134: 9845.6527 | H134: 88571491 | I134: 1.4251957 | J134: 76854 | K134: 76891213389 | L134: US | M134: 45202.595 | N134: 45205.189 | O134: 45215.784 | P134: 10397261234 | Q134: 982022 | S134: 25612510 | T134: 700
A135: 952000089 | B135: 1 | C135: =IF(A135=A134,PurchaseOrder!C134,INDEX(VendTable!$A$2:$A$109,RANDBETWEEN(1,23))) -> 700001 | E135: 2024-01-02T14:16:06.9086921Z | F135: 18460 | G135: 863.00751 | H135: 15931119 | I135: 1.0946828 | J135: 76862 | K135: 76891213314 | L135: US | M135: 45002.595 | N135: 45004.189 | O135: 45009.784 | P135: 10397261234 | Q135: 981986 | S135: 25612474 | T135: 300
A136: 952000091 | B136: 1 | C136: =IF(A136=A135,PurchaseOrder!C135,INDEX(VendTable!$A$2:$A$109,RANDBETWEEN(1,23))) -> 700003 | E136: 2024-01-02T14:16:06.9086921Z | F136: 5166 | G136: 6835.7316 | H136: 35313389 | I136: 1.8459188 | J136: 76871 | K136: 76891213570 | L136: US | M136: 45250.595 | N136: 45251.189 | O136: 45254.784 | P136: 10397261234 | Q136: 981874 | S136: 25612362 | T136: 100
A137: 952000091 | B137: 2 | C137: =IF(A137=A136,PurchaseOrder!C136,INDEX(VendTable!$A$2:$A$109,RANDBETWEEN(1,23))) -> 700003 | E137: 2024-01-02T14:16:06.9086921Z | F137: 11330 | G137: 8766.2439 | H137: 99321543 | I137: 1.388555 | J137: 76858 | K137: 76891213608 | L137: US | M137: 45401.595 | N137: 45403.189 | O137: 45409.784 | P137: 10397261234 | Q137: 981942 | S137: 25612430 | T137: 300
A138: 952000091 | B138: 3 | C138: =IF(A138=A137,PurchaseOrder!C137,INDEX(VendTable!$A$2:$A$109,RANDBETWEEN(1,23))) -> 700003 | E138: 2024-01-02T14:16:06.9086921Z | F138: 28624 | G138: 810.21909 | H138: 23191711 | I138: 1.4468329 | J138: 76865 | K138: 76891213323 | L138: US | M138: 45421.595 | N138: 45422.189 | O138: 45432.784 | P138: 10397261234 | Q138: 981969 | S138: 25612457 | T138: 200
... A195: 952000124 | B195: 2 | C195: =IF(A195=A194,PurchaseOrder!C194,INDEX(VendTable!$A$2:$A$109,RANDBETWEEN(1,23))) -> 700014 | E195: 2024-01-02T14:16:06.9086921Z | F195: 20145 | G195: 2008.824 | H195: 40467759 | I195: 1.3216775 | J195: 76852 | K195: 76891213390 | L195: US | M195: 44870.595 | N195: 44873.189 | O195: 44883.784 | P195: 10397261234 | Q195: 981979 | S195: 25612467 | T195: 500

Sheet PurchItem
A1: ItemId | B1: Txt | C1: LastProcessedChange_DateTime | D1: DataLakeModified_DateTime | E1: ValidFrom | F1: ValidTo | G1: IsActive | H1: Price | I1: RecordId | J1: CategoryID
A2: 76891213142 | B2: =INDEX($R$4:$R$609,RANDBETWEEN(1,606))&"-"&INDEX($S$4:$S$10,RANDBETWEEN(1,7)) -> Lock Nut 3-3T | D2: 2024-01-02T14:16:06.9086921Z | E2: 2010-01-01T14:16:06.9086921Z | G2: 1 | H2: =RANDBETWEEN(100,10000)+RAND() -> 5034.8662 | I2: 34521256 | J2: =INDEX($O$3:$O$12,RANDBETWEEN(1,10)) -> 400
A3: 76891213143 | B3: =INDEX($R$4:$R$609,RANDBETWEEN(1,606))&"-"&INDEX($S$4:$S$10,RANDBETWEEN(1,7)) -> Lock Nut 6-8S | D3: 2024-01-02T14:16:06.9086921Z | E3: 2010-01-01T14:16:06.9086921Z | G3: 1 | H3: =RANDBETWEEN(100,10000)+RAND() -> 2099.5083 | I3: 34521257 | J3: =INDEX($O$3:$O$12,RANDBETWEEN(1,10)) -> 600 | O3: 100
A4: 76891213144 | B4: =INDEX($R$4:$R$609,RANDBETWEEN(1,606))&"-"&INDEX($S$4:$S$10,RANDBETWEEN(1,7)) -> Mountain-400-W Silver, 38-8S | D4: 2024-01-02T14:16:06.9086921Z | E4: 2010-01-01T14:16:06.9086921Z | G4: 1 | H4: =RANDBETWEEN(100,10000)+RAND() -> 4043.8015 | I4: 34521258 | J4: =INDEX($O$3:$O$12,RANDBETWEEN(1,10)) -> 700 | O4: 200 | R4: Adjustable Race | S4: 1T
A5: 76891213145 | B5: =INDEX($R$4:$R$609,RANDBETWEEN(1,606))&"-"&INDEX($S$4:$S$10,RANDBETWEEN(1,7)) -> Guide Pulley-6S | D5: 2024-01-02T14:16:06.9086921Z | E5: 2010-01-01T14:16:06.9086921Z | G5: 1 | H5: =RANDBETWEEN(100,10000)+RAND() -> 9273.3062 | I5: 34521259 | J5: =INDEX($O$3:$O$12,RANDBETWEEN(1,10)) -> 700 | O5: 300 | R5: Bearing Ball | S5: 2T
A6: 76891213146 | B6: =INDEX($R$4:$R$609,RANDBETWEEN(1,606))&"-"&INDEX($S$4:$S$10,RANDBETWEEN(1,7)) -> Mountain-500 Silver, 52-8S | D6: 2024-01-02T14:16:06.9086921Z | E6: 2010-01-01T14:16:06.9086921Z | G6: 1 | H6: =RANDBETWEEN(100,10000)+RAND() -> 5461.8261 | I6: 34521260 | J6: =INDEX($O$3:$O$12,RANDBETWEEN(1,10)) -> 600 | O6: 400 | R6: BB Ball Bearing | S6: 3T
A7: 76891213147 | B7: =INDEX($R$4:$R$609,RANDBETWEEN(1,606))&"-"&INDEX($S$4:$S$10,RANDBETWEEN(1,7)) -> HL Crankarm-9Z | D7: 2024-01-02T14:16:06.9086921Z | E7: 2010-01-01T14:16:06.9086921Z | G7: 1 | H7: =RANDBETWEEN(100,10000)+RAND() -> 2264.3354 | I7: 34521261 | J7: =INDEX($O$3:$O$12,RANDBETWEEN(1,10)) -> 300 | O7: 500 | R7: Headset Ball Bearings | S7: 6S
A8: 76891213148 | B8: =INDEX($R$4:$R$609,RANDBETWEEN(1,606))&"-"&INDEX($S$4:$S$10,RANDBETWEEN(1,7)) -> Road-650 Red, 48-3T | D8: 2024-01-02T14:16:06.9086921Z | E8: 2010-01-01T14:16:06.9086921Z | G8: 1 | H8: =RANDBETWEEN(100,10000)+RAND() -> 1059.7105 | I8: 34521262 | J8: =INDEX($O$3:$O$12,RANDBETWEEN(1,10)) -> 900 | O8: 600 | R8: Blade | S8: 8S
A9: 76891213149 | B9: =INDEX($R$4:$R$609,RANDBETWEEN(1,606))&"-"&INDEX($S$4:$S$10,RANDBETWEEN(1,7)) -> Road-150 Red, 62-2T | D9: 2024-01-02T14:16:06.9086921Z | E9: 2010-01-01T14:16:06.9086921Z | G9: 1 | H9: =RANDBETWEEN(100,10000)+RAND() -> 1501.6372 | I9: 34521263 | J9: =INDEX($O$3:$O$12,RANDBETWEEN(1,10)) -> 400 | O9: 700 | R9: LL Crankarm | S9: 9Z
A10: 76891213150 | B10: =INDEX($R$4:$R$609,RANDBETWEEN(1,606))&"-"&INDEX($S$4:$S$10,RANDBETWEEN(1,7)) -> Thin-Jam Lock Nut 11-8S | D10: 2024-01-02T14:16:06.9086921Z | E10: 2010-01-01T14:16:06.9086921Z | G10: 1 | H10: =RANDBETWEEN(100,10000)+RAND() -> 4841.3946 | I10: 34521264 | J10: =INDEX($O$3:$O$12,RANDBETWEEN(1,10)) -> 300 | O10: 800 | R10: ML Crankarm | S10: 10Z
A11: 76891213151 | B11: =INDEX($R$4:$R$609,RANDBETWEEN(1,606))&"-"&INDEX($S$4:$S$10,RANDBETWEEN(1,7)) -> HL Road Frame - Red, 62-6S | D11: 2024-01-02T14:16:06.9086921Z | E11: 2010-01-01T14:16:06.9086921Z | G11: 1 | H11: =RANDBETWEEN(100,10000)+RAND() -> 6578.949 | I11: 34521265 | J11: =INDEX($O$3:$O$12,RANDBETWEEN(1,10)) -> 900 | O11: 900 | R11: HL Crankarm
A12: 76891213152 | B12: =INDEX($R$4:$R$609,RANDBETWEEN(1,606))&"-"&INDEX($S$4:$S$10,RANDBETWEEN(1,7)) -> Reflector-8S | D12: 2024-01-02T14:16:06.9086921Z | E12: 2010-01-01T14:16:06.9086921Z | G12: 1 | H12: =RANDBETWEEN(100,10000)+RAND() -> 169.38212 | I12: 34521266 | J12: =INDEX($O$3:$O$12,RANDBETWEEN(1,10)) -> 400 | O12: 1000 | R12: Chainring Bolts
A13: 76891213153 | B13: =INDEX($R$4:$R$609,RANDBETWEEN(1,606))&"-"&INDEX($S$4:$S$10,RANDBETWEEN(1,7)) -> LL Road Frame - Red, 44-3T | D13: 2024-01-02T14:16:06.9086921Z | E13: 2010-01-01T14:16:06.9086921Z | G13: 1 | H13: =RANDBETWEEN(100,10000)+RAND() -> 9849.995 | I13: 34521267 | J13: =INDEX($O$3:$O$12,RANDBETWEEN(1,10)) -> 1000 | R13: Chainring Nut
A14: 76891213154 | B14: =INDEX($R$4:$R$609,RANDBETWEEN(1,606))&"-"&INDEX($S$4:$S$10,RANDBETWEEN(1,7)) -> Lock Nut 13-6S | D14: 2024-01-02T14:16:06.9086921Z | E14: 2010-01-01T14:16:06.9086921Z | G14: 1 | H14: =RANDBETWEEN(100,10000)+RAND() -> 5837.3436 | I14: 34521268 | J14: =INDEX($O$3:$O$12,RANDBETWEEN(1,10)) -> 400 | R14: Chainring
A15: 76891213155 | B15: =INDEX($R$4:$R$609,RANDBETWEEN(1,606))&"-"&INDEX($S$4:$S$10,RANDBETWEEN(1,7)) -> HL Road Front Wheel-3T | D15: 2024-01-02T14:16:06.9086921Z | E15: 2010-01-01T14:16:06.9086921Z | G15: 1 | H15: =RANDBETWEEN(100,10000)+RAND() -> 3627.1919 | I15: 34521269 | J15: =INDEX($O$3:$O$12,RANDBETWEEN(1,10)) -> 200 | R15: Crown Race
A16: 76891213156 | B16: =INDEX($R$4:$R$609,RANDBETWEEN(1,606))&"-"&INDEX($S$4:$S$10,RANDBETWEEN(1,7)) -> ML Mountain Handlebars-2T | D16: 2024-01-02T14:16:06.9086921Z | E16: 2010-01-01T14:16:06.9086921Z | G16: 1 | H16: =RANDBETWEEN(100,10000)+RAND() -> 9558.6946 | I16: 34521270 | J16: =INDEX($O$3:$O$12,RANDBETWEEN(1,10)) -> 700 | R16: Chain Stays
A17: 76891213157 | B17: =INDEX($R$4:$R$609,RANDBETWEEN(1,606))&"-"&INDEX($S$4:$S$10,RANDBETWEEN(1,7)) -> Lock Washer 2-3T | D17: 2024-01-02T14:16:06.9086921Z | E17: 2010-01-01T14:16:06.9086921Z | G17: 1 | H17: =RANDBETWEEN(100,10000)+RAND() -> 8322.4899 | I17: 34521271 | J17: =INDEX($O$3:$O$12,RANDBETWEEN(1,10)) -> 100 | R17: Decal 1
A18: 76891213158 | B18: =INDEX($R$4:$R$609,RANDBETWEEN(1,606))&"-"&INDEX($S$4:$S$10,RANDBETWEEN(1,7)) -> Cone-Shaped Race-3T | D18: 2024-01-02T14:16:06.9086921Z | E18: 2010-01-01T14:16:06.9086921Z | G18: 1 | H18: =RANDBETWEEN(100,10000)+RAND() -> 7429.0949 | I18: 34521272 | J18: =INDEX($O$3:$O$12,RANDBETWEEN(1,10)) -> 600 | R18: Decal 2
A19: 76891213159 | B19: =INDEX($R$4:$R$609,RANDBETWEEN(1,606))&"-"&INDEX($S$4:$S$10,RANDBETWEEN(1,7)) -> HL Road Frame - Red, 56-1T | D19: 2024-01-02T14:16:06.9086921Z | E19: 2010-01-01T14:16:06.9086921Z | G19: 1 | H19: =RANDBETWEEN(100,10000)+RAND() -> 1020.1296 | I19: 34521273 | J19: =INDEX($O$3:$O$12,RANDBETWEEN(1,10)) -> 400 | R19: Down Tube
A20: 76891213160 | B20: =INDEX($R$4:$R$609,RANDBETWEEN(1,606))&"-"&INDEX($S$4:$S$10,RANDBETWEEN(1,7)) -> Lock Washer 12-8S | D20: 2024-01-02T14:16:06.9086921Z | E20: 2010-01-01T14:16:06.9086921Z | G20: 1 | H20: =RANDBETWEEN(100,10000)+RAND() -> 8462.977 | I20: 34521274 | J20: =INDEX($O$3:$O$12,RANDBETWEEN(1,10)) -> 700 | R20: Mountain End Caps
A21: 76891213161 | B21: =INDEX($R$4:$R$609,RANDBETWEEN(1,606))&"-"&INDEX($S$4:$S$10,RANDBETWEEN(1,7)) -> Metal Angle-1T | D21: 2024-01-02T14:16:06.9086921Z | E21: 2010-01-01T14:16:06.9086921Z | G21: 1 | H21: =RANDBETWEEN(100,10000)+RAND() -> 4626.4083 | I21: 34521275 | J21: =INDEX($O$3:$O$12,RANDBETWEEN(1,10)) -> 500 | R21: Road End Caps
A22: 76891213162 | B22: =INDEX($R$4:$R$609,RANDBETWEEN(1,606))&"-"&INDEX($S$4:$S$10,RANDBETWEEN(1,7)) -> Road-650 Red, 60-10Z | D22: 2024-01-02T14:16:06.9086921Z | E22: 2010-01-01T14:16:06.9086921Z | G22: 1 | H22: =RANDBETWEEN(100,10000)+RAND() -> 4691.9231 | I22: 34521276 | J22: =INDEX($O$3:$O$12,RANDBETWEEN(1,10)) -> 600 | R22: Touring End Caps
A23: 76891213163 | B23: =INDEX($R$4:$R$609,RANDBETWEEN(1,606))&"-"&INDEX($S$4:$S$10,RANDBETWEEN(1,7)) -> Paint - Blue-2T | D23: 2024-01-02T14:16:06.9086921Z | E23: 2010-01-01T14:16:06.9086921Z | G23: 1 | H23: =RANDBETWEEN(100,10000)+RAND() -> 8353.8076 | I23: 34521277 | J23: =INDEX($O$3:$O$12,RANDBETWEEN(1,10)) -> 700 | R23: Fork End
A24: 76891213164 | B24: =INDEX($R$4:$R$609,RANDBETWEEN(1,606))&"-"&INDEX($S$4:$S$10,RANDBETWEEN(1,7)) -> HL Mountain Frame - Black, 42-1T | D24: 2024-01-02T14:16:06.9086921Z | E24: 2010-01-01T14:16:06.9086921Z | G24: 1 | H24: =RANDBETWEEN(100,10000)+RAND() -> 7433.816 | I24: 34521278 | J24: =INDEX($O$3:$O$12,RANDBETWEEN(1,10)) -> 100 | R24: Freewheel
... A508: 76891213648 | B508: =INDEX($R$4:$R$609,RANDBETWEEN(1,606))&"-"&INDEX($S$4:$S$10,RANDBETWEEN(1,7)) -> Mountain-200 Black, 42-3T | D508: 2024-01-02T14:16:06.9086921Z | E508: 2010-01-01T14:16:06.9086921Z | G508: 1 | H508: =RANDBETWEEN(100,10000)+RAND() -> 2614.0754 | I508: 34521762 | J508: =INDEX($O$3:$O$12,RANDBETWEEN(1,10)) -> 200 | R508: LL Touring Frame - Blue, 62
R509: LL Touring Frame - Yellow, 44
R510: LL Touring Frame - Yellow, 50
R511: LL Touring Frame - Yellow, 54
R512: LL Touring Frame - Yellow, 58
R513: LL Touring Frame - Blue, 44
R514: ML Mountain Frame-W - Silver, 40
R515: ML Mountain Frame-W - Silver, 42
R516: ML Mountain Frame-W - Silver, 46
R517: Rear Brakes
R518: LL Mountain Seat/Saddle
R519: ML Mountain Seat/Saddle
R520: HL Mountain Seat/Saddle
... R609: Road-750 Black, 52

Sheet PurchCategory
A1: CategoryId | B1: CategoryName | C1: LastProcessedChange_DateTime | D1: DataLakeModified_DateTime | E1: CategoryGroupId | F1: RecordId
A2: 100 | B2: Utilities | D2: 2024-01-02T14:16:06.9086921Z | E2: 1 | F2: 29836432
A3: 200 | B3: Food | D3: 2024-01-02T14:16:06.9086921Z | E3: 2 | F3: 29836433
A4: 300 | B4: Beverages | D4: 2024-01-02T14:16:06.9086921Z | E4: 2 | F4: 29836434
A5: 400 | B5: Meat | D5: 2024-01-02T14:16:06.9086921Z | E5: 2 | F5: 29836435
A6: 500 | B6: Stationary | D6: 2024-01-02T14:16:06.9086921Z | E6: 3 | F6: 29836436
A7: 600 | B7: Kids | D7: 2024-01-02T14:16:06.9086921Z | E7: 4 | F7: 29836437
A8: 700 | B8: Adult | D8: 2024-01-02T14:16:06.9086921Z | E8: 5 | F8: 29836438
A9: 800 | B9: Electronics | D9: 2024-01-02T14:16:06.9086921Z | E9: 6 | F9: 29836439
A10: 900 | B10: Clothing | D10: 2024-01-02T14:16:06.9086921Z | E10: 7 | F10: 29836440
A11: 1000 | B11: Bathing | D11: 2024-01-02T14:16:06.9086921Z | E11: 8 | F11: 29836441

Sheet SilverTables

Sheet dirparty
E1: JoinKey
C2: Tables | D2: parties | E2: PartyId
D3: partyaddress | E3: PartyNumber
C5: ColumnsNeeded | D5: If name is blank, retain the original column name
C7: Table | D7: Column | E7: Logic | F7: Name
C8: parties | D8: PartyId
C9: parties | D9: PartyName
C10: parties | D10: LastProcessedChange_DateTime
C11: parties | D11: DataLakeModified_DateTime | E11: ConvertToCST
C12: parties | D12: PartyAddressCode
C13: parties | D13: EstablishedDate | E13: ConvertToCST
C14: parties | D14: PartyEmailId
C15: parties | D15: PartyContactNumber
C16: parties | D16: RecordId | F16: PartyRecordId
C17: parties | D17: TaxId
C18: partyaddress | D18: Address
C19: partyaddress | D19: City
C20: partyaddress | D20: State
C21: partyaddress | D21: Country
C22: partyaddress | D22: ZipCode
C23: partyaddress | D23: Region
C24: partyaddress | D24: ValidFrom | E24: ConvertToCST
C25: partyaddress | D25: ValidTo | E25: ConvertToCST
C26: partyaddress | D26: RecordId | F26: PartyAddressRecordId

Sheet dirvendor
C2: Tables | D2: VendTable
C5: ColumnsNeeded | D5: If name is blank, retain the original column name
C7: Table | D7: Column | E7: Logic | F7: Name | G7: Comments
C8: VendTable | D8: VendId | F8: VendorId
C9: VendTable | D9: VendorName
C10: VendTable | D10: LastProcessedChange_DateTime
C11: VendTable | D11: DataLakeModified_DateTime | E11: ConvertToCST
C12: VendTable | D12: Address
C13: VendTable | D13: City
C14: VendTable | D14: State
C15: VendTable | D15: Country
C16: VendTable | D16: ZipCode
C17: VendTable | D17: Region
C18: VendTable | D18: ValidFrom | E18: ConvertToCST
C19: VendTable | D19: ValidTo | E19: ConvertToCST
C20: VendTable | D20: Active
C21: VendTable | D21: RecordId | F21: VendorRecordId
C22: VendTable | D22: TaxId
C23: VendTable | D23: CurrencyCode
C24: VendTable | D24: VendorDiscount | E24: See Comments | G24: If the vendor is based in US, the discount should be 1%, if in UK, the discount should be 0.6% and 0 for rest

Sheet dirpurchcategory
C2: Tables | D2: PurchCategory
C5: ColumnsNeeded | D5: If name is blank, retain the original column name
C7: Table | D7: Column | E7: Logic | F7: Name
C8: PurchCategory | D8: CategoryId
C9: PurchCategory | D9: CategoryName
C10: PurchCategory | D10: LastProcessedChange_DateTime
C11: PurchCategory | D11: DataLakeModified_DateTime | E11: ConvertToCST
C12: PurchCategory | D12: CategoryGroupId
C13: PurchCategory | D13: RecordId | F13: PurchCategoryRecordId

Sheet dirpurchitem
C2: Tables | D2: PurchItem
C5: ColumnsNeeded | D5: If name is blank, retain the original column name
C7: Table | D7: Column | E7: Logic | F7: Name
C8: PurchItem | D8: ItemId
C9: PurchItem | D9: Txt | F9: ProductName
C10: PurchItem | D10: LastProcessedChange_DateTime
C11: PurchItem | D11: DataLakeModified_DateTime | E11: ConvertToCST
C12: PurchItem | D12: ValidFrom | E12: ConvertToCST
C13: PurchItem | D13: ValidTo | E13: ConvertToCST
C14: PurchItem | D14: Price | F14: ProductPerUnitCost
C15: PurchItem | D15: RecordId | F15: PurchItemRecordId
C16: PurchItem | D16: CategoryID

Sheet dircostcenter
C2: Tables | D2: CostCenter
C5: ColumnsNeeded | D5: If name is blank, retain the original column name
C7: Table | D7: Column | E7: Logic | F7: Name
C8: CostCenter | D8: CostCenterNumber
C9: CostCenter | D9: LastProcessedChange_DateTime
C10: CostCenter | D10: DataLakeModified_DateTime | E10: ConvertToCST
C11: CostCenter | D11: Vat
C12: CostCenter | D12: RecordId | F12: CostCenterRecordId

Sheet costcenter
A1: CostCenterNumber | B1: LastProcessedChange_DateTime | C1: DataLakeModified_DateTime | D1: Vat
A2: 76852 | C2: 2024-01-02T14:16:06.9086921Z | D2: =RANDBETWEEN(4,6.5)/100 -> 0.06
A3: 76853 | C3: 2024-01-02T14:16:06.9086921Z | D3: =RANDBETWEEN(4,6.5)/100 -> 0.05
A4: 76854 | C4: 2024-01-02T14:16:06.9086921Z | D4: =RANDBETWEEN(4,6.5)/100 -> 0.04
A5: 76855 | C5: 2024-01-02T14:16:06.9086921Z | D5: =RANDBETWEEN(4,6.5)/100 -> 0.06
A6: 76856 | C6: 2024-01-02T14:16:06.9086921Z | D6: =RANDBETWEEN(4,6.5)/100 -> 0.05
A7: 76857 | C7: 2024-01-02T14:16:06.9086921Z | D7: =RANDBETWEEN(4,6.5)/100 -> 0.06
A8: 76858 | C8: 2024-01-02T14:16:06.9086921Z | D8: =RANDBETWEEN(4,6.5)/100 -> 0.05
A9: 76859 | C9: 2024-01-02T14:16:06.9086921Z | D9: =RANDBETWEEN(4,6.5)/100 -> 0.05
A10: 76860 | C10: 2024-01-02T14:16:06.9086921Z | D10: =RANDBETWEEN(4,6.5)/100 -> 0.04
A11: 76861 | C11: 2024-01-02T14:16:06.9086921Z | D11: =RANDBETWEEN(4,6.5)/100 -> 0.06
A12: 76862 | C12: 2024-01-02T14:16:06.9086921Z | D12: =RANDBETWEEN(4,6.5)/100 -> 0.04
A13: 76863 | C13: 2024-01-02T14:16:06.9086921Z | D13: =RANDBETWEEN(4,6.5)/100 -> 0.04
... A24: 76874 | C24: 2024-01-02T14:16:06.9086921Z | D24: =RANDBETWEEN(4,6.5)/100 -> 0.06

Sheet factpurchaseorder
C1: Table | D1: JoinKey | E1: Table | F1: JoinKey
C3: PurchaseOrder | D3: CostCenter | E3: dimcostcenter | F3: CostCenterNumber
C4: PurchaseOrder | D4: Itemkey | E4: dimpurchitem | F4: ItemId
C5: PurchaseOrder | D5: currencycode | E5: dimcurrency | F5: CurrencyCode
C8: ColumnsNeeded | D8: If name is blank, retain the original column name
C10: Table | D10: Column | E10: Logic | F10: Name | G10: Comments
C11: PurchaseOrder | D11: PoNumber
C12: PurchaseOrder | D12: LineItem
C13: PurchaseOrder | D13: VendId | F13: VendorKey
C14: PurchaseOrder | D14: LastProcessedChange_DateTime
C15: PurchaseOrder | D15: DataLakeModified_DateTime | E15: ConvertToCST
C16: PurchaseOrder | D16: Qty
C17: PurchaseOrder | D17: PurchasePrice
C18: PurchaseOrder | D18: TotalOrder
C19: PurchaseOrder | D19: CostCenter | F19: CostCenterKey
C20: CostCenter | D20: Vat | F20: VatAmount
D21: TotalAmount | E21: TotalOrder + (TotalOrder * Vat) | F21: TotalAmount | G21: Round to 4 digits
C22: PurchaseOrder | D22: ExchangeRate
C23: PurchaseOrder | D23: Itemkey
C24: dimcurrency | D24: CurrencyId | F24: CurrencyKey
C25: PurchaseOrder | D25: OrderDate | E25: ConvertToCST
C26: PurchaseOrder | D26: ShipDate | E26: ConvertToCST
C27: PurchaseOrder | D27: DeliveredDate | E27: ConvertToCST
C28: PurchaseOrder | D28: OrderDate | E28: Cast to int | F28: OrderDateKey
C29: PurchaseOrder | D29: ShipDate | E29: Cast to int | F29: ShipDateKey
C30: PurchaseOrder | D30: DeliveredDate | E30: Cast to int | F30: DeliveredDateKey
C31: PurchaseOrder | D31: TrackingNumber
C32: PurchaseOrder | D32: Batchid | F32: BatchId
C33: PurchaseOrder | D33: CreatedBy
C34: PurchaseOrder | D34: RecordId | F34: PurchaseOrderRecordId
C35: PurchaseOrder | D35: CategoryID | F35: CategoryKey

Sheet Sales

Sheet SalesOrderLine
A1: SalesOrderNumber | B1: LastProcessedChange_DateTime | C1: DataLakeModified_DateTime | D1: SalesOrderLine | E1: ItemId | F1: Qty | G1: Price | H1: VatPercentage | I1: CurrencyCode | J1: BookDate | K1: ShippedDate | L1: DeliveredDate | M1: TrackingNumber | N1: CustId | O1: PaymentTypeDesc | P1: RecordId
A2: 93827211982 | C2: 2024-01-02T14:16:06.9086921Z | D2: 1 | E2: 76891213323 | F2: =RANDBETWEEN(1,100) -> 65 | G2: =VLOOKUP(E2,PurchItem!$A$2:$H$508,8,0) -> 2479.1592 | H2: 0.04 | I2: USD | J2: 44601.595 | K2: 44602.189 | L2: 44608.784 | M2: 10029727212 | N2: 11000 | O2: CreditCard | P2: 52936136
A3: 93827211982 | C3: 2024-01-02T14:16:06.9086921Z | D3: 2 | E3: 76891213151 | F3: =RANDBETWEEN(1,100) -> 79 | G3: =VLOOKUP(E3,PurchItem!$A$2:$H$508,8,0) -> 6578.949 | H3: 0.05 | I3: USD | J3: 44933.595 | K3: 44935.189 | L3: 44942.784 | M3: =IF(A3<>A2,M2+1,M2) -> 10029727212 | N3: =IF(M3<>M2,INDEX(CustInfo!$A$2:$A$1001,RANDBETWEEN(1,1000)),N2) -> 11000 | O3: CreditCard | P3: 52936137
A4: 93827211982 | C4: 2024-01-02T14:16:06.9086921Z | D4: 3 | E4: 76891213394 | F4: =RANDBETWEEN(1,100) -> 52 | G4: =VLOOKUP(E4,PurchItem!$A$2:$H$508,8,0) -> 4295.2255 | H4: 0.04 | I4: USD | J4: 45524.595 | K4: 45525.189 | L4: 45527.784 | M4: =IF(A4<>A3,M3+1,M3) -> 10029727212 | N4: =IF(M4<>M3,INDEX(CustInfo!$A$2:$A$1001,RANDBETWEEN(1,1000)),N3) -> 11000 | O4: CreditCard | P4: 52936138
A5: 93827211982 | C5: 2024-01-02T14:16:06.9086921Z | D5: 4 | E5: 76891213290 | F5: =RANDBETWEEN(1,100) -> 84 | G5: =VLOOKUP(E5,PurchItem!$A$2:$H$508,8,0) -> 8789.9228 | H5: 0.05 | I5: USD | J5: 45282.595 | K5: 45283.189 | L5: 45293.784 | M5: =IF(A5<>A4,M4+1,M4) -> 10029727212 | N5: =IF(M5<>M4,INDEX(CustInfo!$A$2:$A$1001,RANDBETWEEN(1,1000)),N4) -> 11000 | O5: CreditCard | P5: 52936139
A6: 93827211983 | C6: 2024-01-02T14:16:06.9086921Z | D6: 1 | E6: 76891213486 | F6: =RANDBETWEEN(1,100) -> 21 | G6: =VLOOKUP(E6,PurchItem!$A$2:$H$508,8,0) -> 9918.4804 | H6: 0.05 | I6: USD | J6: 44715.595 | K6: 44719.189 | L6: 44727.784 | M6: =IF(A6<>A5,M5+1,M5) -> 10029727213 | N6: =IF(M6<>M5,INDEX(CustInfo!$A$2:$A$1001,RANDBETWEEN(1,1000)),N5) -> 11984 | O6: CashOnDelivery | P6: 52936140
A7: 93827211983 | C7: 2024-01-02T14:16:06.9086921Z | D7: 2 | E7: 76891213442 | F7: =RANDBETWEEN(1,100) -> 35 | G7: =VLOOKUP(E7,PurchItem!$A$2:$H$508,8,0) -> 3996.4553 | H7: 0.04 | I7: USD | J7: 44983.595 | K7: 44986.189 | L7: 44986.784 | M7: =IF(A7<>A6,M6+1,M6) -> 10029727213 | N7: =IF(M7<>M6,INDEX(CustInfo!$A$2:$A$1001,RANDBETWEEN(1,1000)),N6) -> 11984 | O7: CashOnDelivery | P7: 52936141
A8: 93827211983 | C8: 2024-01-02T14:16:06.9086921Z | D8: 3 | E8: 76891213468 | F8: =RANDBETWEEN(1,100) -> 18 | G8: =VLOOKUP(E8,PurchItem!$A$2:$H$508,8,0) -> 8720.5574 | H8: 0.06 | I8: USD | J8: 45193.595 | K8: 45195.189 | L8: 45205.784 | M8: =IF(A8<>A7,M7+1,M7) -> 10029727213 | N8: =IF(M8<>M7,INDEX(CustInfo!$A$2:$A$1001,RANDBETWEEN(1,1000)),N7) -> 11984 | O8: CashOnDelivery | P8: 52936142
A9: 93827211984 | C9: 2024-01-02T14:16:06.9086921Z | D9: 1 | E9: 76891213526 | F9: =RANDBETWEEN(1,100) -> 17 | G9: =VLOOKUP(E9,PurchItem!$A$2:$H$508,8,0) -> 8212.805 | H9: 0.04 | I9: USD | J9: 44916.595 | K9: 44920.189 | L9: 44927.784 | M9: =IF(A9<>A8,M8+1,M8) -> 10029727214 | N9: =IF(M9<>M8,INDEX(CustInfo!$A$2:$A$1001,RANDBETWEEN(1,1000)),N8) -> 11240 | O9: DebitCard | P9: 52936143
A10: 93827211984 | C10: 2024-01-02T14:16:06.9086921Z | D10: 2 | E10: 76891213249 | F10: =RANDBETWEEN(1,100) -> 50 | G10: =VLOOKUP(E10,PurchItem!$A$2:$H$508,8,0) -> 8086.2833 | H10: 0.04 | I10: USD | J10: 44860.595 | K10: 44863.189 | L10: 44863.784 | M10: =IF(A10<>A9,M9+1,M9) -> 10029727214 | N10: =IF(M10<>M9,INDEX(CustInfo!$A$2:$A$1001,RANDBETWEEN(1,1000)),N9) -> 11240 | O10: DebitCard | P10: 52936144
A11: 93827211985 | C11: 2024-01-02T14:16:06.9086921Z | D11: 1 | E11: 76891213362 | F11: =RANDBETWEEN(1,100) -> 59 | G11: =VLOOKUP(E11,PurchItem!$A$2:$H$508,8,0) -> 2524.8525 | H11: 0.06 | I11: USD | J11: 45302.595 | K11: 45304.189 | L11: 45313.784 | M11: =IF(A11<>A10,M10+1,M10) -> 10029727215 | N11: =IF(M11<>M10,INDEX(CustInfo!$A$2:$A$1001,RANDBETWEEN(1,1000)),N10) -> 11873 | O11: DebitCard | P11: 52936145
A12: 93827211986 | C12: 2024-01-02T14:16:06.9086921Z | D12: 1 | E12: 76891213284 | F12: =RANDBETWEEN(1,100) -> 38 | G12: =VLOOKUP(E12,PurchItem!$A$2:$H$508,8,0) -> 8438.9293 | H12: 0.06 | I12: USD | J12: 44900.595 | K12: 44903.189 | L12: 44906.784 | M12: =IF(A12<>A11,M11+1,M11) -> 10029727216 | N12: =IF(M12<>M11,INDEX(CustInfo!$A$2:$A$1001,RANDBETWEEN(1,1000)),N11) -> 11619 | O12: DebitCard | P12: 52936146
A13: 93827211987 | C13: 2024-01-02T14:16:06.9086921Z | D13: 1 | E13: 76891213184 | F13: =RANDBETWEEN(1,100) -> 48 | G13: =VLOOKUP(E13,PurchItem!$A$2:$H$508,8,0) -> 5805.119 | H13: 0.05 | I13: USD | J13: 44643.595 | K13: 44646.189 | L13: 44655.784 | M13: =IF(A13<>A12,M12+1,M12) -> 10029727217 | N13: =IF(M13<>M12,INDEX(CustInfo!$A$2:$A$1001,RANDBETWEEN(1,1000)),N12) -> 11969 | O13: CreditCard | P13: 52936147
A14: 93827211987 | C14: 2024-01-02T14:16:06.9086921Z | D14: 2 | E14: 76891213555 | F14: =RANDBETWEEN(1,100) -> 84 | G14: =VLOOKUP(E14,PurchItem!$A$2:$H$508,8,0) -> 6639.1318 | H14: 0.04 | I14: USD | J14: 45037.595 | K14: 45041.189 | L14: 45049.784 | M14: =IF(A14<>A13,M13+1,M13) -> 10029727217 | N14: =IF(M14<>M13,INDEX(CustInfo!$A$2:$A$1001,RANDBETWEEN(1,1000)),N13) -> 11969 | O14: CreditCard | P14: 52936148
... A125: 93827212028 | C125: 2024-01-02T14:16:06.9086921Z | D125: 2 | E125: 76891213371 | F125: =RANDBETWEEN(1,100) -> 98 | G125: =VLOOKUP(E125,PurchItem!$A$2:$H$508,8,0) -> 2898.9854 | H125: 0.06 | I125: USD | J125: 45409.595 | K125: 45412.189 | L125: 45417.784 | M125: =IF(A125<>A124,M124+1,M124) -> 10029727258 | N125: =IF(M125<>M124,INDEX(CustInfo!$A$2:$A$1001,RANDBETWEEN(1,1000)),N124) -> 11863 | O125: DebitCard | P125: 52936259
A126: 93827212028 | C126: 2024-01-02T14:16:06.9086921Z | D126: 3 | E126: 76891213551 | F126: =RANDBETWEEN(1,100) -> 53 | G126: =VLOOKUP(E126,PurchItem!$A$2:$H$508,8,0) -> 8257.6439 | H126: 0.06 | I126: USD | J126: =RANDBETWEEN(DATE(2022,1,1),TODAY()-30)+$U$2 -> 45468 | K126: =J126+RANDBETWEEN(0,3)+$U$2 -> 45468 | L126: =K126+RANDBETWEEN(0,10)+$U$2 -> 45468 | M126: =IF(A126<>A125,M125+1,M125) -> 10029727258 | N126: =IF(M126<>M125,INDEX(CustInfo!$A$2:$A$1001,RANDBETWEEN(1,1000)),N125) -> 11863 | O126: DebitCard | P126: 52936260
A127: 93827212028 | C127: 2024-01-02T14:16:06.9086921Z | D127: 4 | E127: 76891213336 | F127: =RANDBETWEEN(1,100) -> 11 | G127: =VLOOKUP(E127,PurchItem!$A$2:$H$508,8,0) -> 2324.4801 | H127: 0.04 | I127: USD | J127: 44774.595 | K127: 44776.189 | L127: 44786.784 | M127: =IF(A127<>A126,M126+1,M126) -> 10029727258 | N127: =IF(M127<>M126,INDEX(CustInfo!$A$2:$A$1001,RANDBETWEEN(1,1000)),N126) -> 11863 | O127: DebitCard | P127: 52936261
A128: 93827212029 | C128: 2024-01-02T14:16:06.9086921Z | D128: 1 | E128: 76891213251 | F128: =RANDBETWEEN(1,100) -> 21 | G128: =VLOOKUP(E128,PurchItem!$A$2:$H$508,8,0) -> 1404.0728 | H128: 0.04 | I128: USD | J128: 45569.595 | K128: 45571.189 | L128: 45572.784 | M128: =IF(A128<>A127,M127+1,M127) -> 10029727259 | N128: =IF(M128<>M127,INDEX(CustInfo!$A$2:$A$1001,RANDBETWEEN(1,1000)),N127) -> 11873 | O128: DebitCard | P128: 52936262
A129: 93827212029 | C129: 2024-01-02T14:16:06.9086921Z | D129: 2 | E129: 76891213601 | F129: =RANDBETWEEN(1,100) -> 58 | G129: =VLOOKUP(E129,PurchItem!$A$2:$H$508,8,0) -> 3260.9614 | H129: 0.04 | I129: USD | J129: 44605.595 | K129: 44609.189 | L129: 44612.784 | M129: =IF(A129<>A128,M128+1,M128) -> 10029727259 | N129: =IF(M129<>M128,INDEX(CustInfo!$A$2:$A$1001,RANDBETWEEN(1,1000)),N128) -> 11873 | O129: DebitCard | P129: 52936263
A130: 93827212029 | C130: 2024-01-02T14:16:06.9086921Z | D130: 3 | E130: 76891213592 | F130: =RANDBETWEEN(1,100) -> 37 | G130: =VLOOKUP(E130,PurchItem!$A$2:$H$508,8,0) -> 4470.4136 | H130: 0.04 | I130: USD | J130: 45491.595 | K130: 45493.189 | L130: 45496.784 | M130: =IF(A130<>A129,M129+1,M129) -> 10029727259 | N130: =IF(M130<>M129,INDEX(CustInfo!$A$2:$A$1001,RANDBETWEEN(1,1000)),N129) -> 11873 | O130: DebitCard | P130: 52936264
A131: 93827212030 | C131: 2024-01-02T14:16:06.9086921Z | D131: 1 | E131: 76891213609 | F131: =RANDBETWEEN(1,100) -> 47 | G131: =VLOOKUP(E131,PurchItem!$A$2:$H$508,8,0) -> 9297.0289 | H131: 0.04 | I131: USD | J131: 45521.595 | K131: 45523.189 | L131: 45531.784 | M131: =IF(A131<>A130,M130+1,M130) -> 10029727260 | N131: =IF(M131<>M130,INDEX(CustInfo!$A$2:$A$1001,RANDBETWEEN(1,1000)),N130) -> 11792 | O131: DebitCard | P131: 52936265
A132: 93827212031 | C132: 2024-01-02T14:16:06.9086921Z | D132: 1 | E132: 76891213277 | F132: =RANDBETWEEN(1,100) -> 57 | G132: =VLOOKUP(E132,PurchItem!$A$2:$H$508,8,0) -> 424.15139 | H132: 0.06 | I132: USD | J132: 45590.595 | K132: 45593.189 | L132: 45600.784 | M132: =IF(A132<>A131,M131+1,M131) -> 10029727261 | N132: =IF(M132<>M131,INDEX(CustInfo!$A$2:$A$1001,RANDBETWEEN(1,1000)),N131) -> 11830 | O132: CashOnDelivery | P132: 52936266
A133: 93827212031 | C133: 2024-01-02T14:16:06.9086921Z | D133: 2 | E133: 76891213273 | F133: =RANDBETWEEN(1,100) -> 71 | G133: =VLOOKUP(E133,PurchItem!$A$2:$H$508,8,0) -> 3906.591 | H133: 0.06 | I133: USD | J133: 45408.595 | K133: 45411.189 | L133: 45416.784 | M133: =IF(A133<>A132,M132+1,M132) -> 10029727261 | N133: =IF(M133<>M132,INDEX(CustInfo!$A$2:$A$1001,RANDBETWEEN(1,1000)),N132) -> 11830 | O133: CashOnDelivery | P133: 52936267
A134: 93827212032 | C134: 2024-01-02T14:16:06.9086921Z | D134: 1 | E134: 76891213220 | F134: =RANDBETWEEN(1,100) -> 98 | G134: =VLOOKUP(E134,PurchItem!$A$2:$H$508,8,0) -> 2008.1764 | H134: 0.05 | I134: USD | J134: 45202.595 | K134: 45205.189 | L134: 45215.784 | M134: =IF(A134<>A133,M133+1,M133) -> 10029727262 | N134: =IF(M134<>M133,INDEX(CustInfo!$A$2:$A$1001,RANDBETWEEN(1,1000)),N133) -> 11680 | O134: DebitCard | P134: 52936268
A135: 93827212032 | C135: 2024-01-02T14:16:06.9086921Z | D135: 2 | E135: 76891213360 | F135: =RANDBETWEEN(1,100) -> 51 | G135: =VLOOKUP(E135,PurchItem!$A$2:$H$508,8,0) -> 6087.4433 | H135: 0.04 | I135: USD | J135: 45002.595 | K135: 45004.189 | L135: 45009.784 | M135: =IF(A135<>A134,M134+1,M134) -> 10029727262 | N135: =IF(M135<>M134,INDEX(CustInfo!$A$2:$A$1001,RANDBETWEEN(1,1000)),N134) -> 11680 | O135: DebitCard | P135: 52936269
A136: 93827212032 | C136: 2024-01-02T14:16:06.9086921Z | D136: 3 | E136: 76891213571 | F136: =RANDBETWEEN(1,100) -> 25 | G136: =VLOOKUP(E136,PurchItem!$A$2:$H$508,8,0) -> 3575.5287 | H136: 0.06 | I136: USD | J136: 45250.595 | K136: 45251.189 | L136: 45254.784 | M136: =IF(A136<>A135,M135+1,M135) -> 10029727262 | N136: =IF(M136<>M135,INDEX(CustInfo!$A$2:$A$1001,RANDBETWEEN(1,1000)),N135) -> 11680 | O136: DebitCard | P136: 52936270
A137: 93827212032 | C137: 2024-01-02T14:16:06.9086921Z | D137: 4 | E137: 76891213601 | F137: =RANDBETWEEN(1,100) -> 62 | G137: =VLOOKUP(E137,PurchItem!$A$2:$H$508,8,0) -> 3260.9614 | H137: 0.05 | I137: USD | J137: 45401.595 | K137: 45403.189 | L137: 45409.784 | M137: =IF(A137<>A136,M136+1,M136) -> 10029727262 | N137: =IF(M137<>M136,INDEX(CustInfo!$A$2:$A$1001,RANDBETWEEN(1,1000)),N136) -> 11680 | O137: DebitCard | P137: 52936271
A138: 93827212033 | C138: 2024-01-02T14:16:06.9086921Z | D138: 1 | E138: 76891213334 | F138: =RANDBETWEEN(1,100) -> 26 | G138: =VLOOKUP(E138,PurchItem!$A$2:$H$508,8,0) -> 8701.4874 | H138: 0.04 | I138: USD | J138: 45421.595 | K138: 45422.189 | L138: 45432.784 | M138: =IF(A138<>A137,M137+1,M137) -> 10029727263 | N138: =IF(M138<>M137,INDEX(CustInfo!$A$2:$A$1001,RANDBETWEEN(1,1000)),N137) -> 11338 | O138: CashOnDelivery | P138: 52936272
... A195: 93827212051 | C195: 2024-01-02T14:16:06.9086921Z | D195: 3 | E195: 76891213551 | F195: =RANDBETWEEN(1,100) -> 89 | G195: =VLOOKUP(E195,PurchItem!$A$2:$H$508,8,0) -> 8257.6439 | H195: 0.05 | I195: USD | J195: 44870.595 | K195: 44873.189 | L195: 44883.784 | M195: =IF(A195<>A194,M194+1,M194) -> 10029727281 | N195: =IF(M195<>M194,INDEX(CustInfo!$A$2:$A$1001,RANDBETWEEN(1,1000)),N194) -> 11333 | O195: CreditCard | P195: 52936329
A196: 93827212052 | C196: 2024-01-02T14:16:06.9086921Z | D196: 1 | E196: 76891213492 | F196: =RANDBETWEEN(1,100) -> 23 | G196: =VLOOKUP(E196,PurchItem!$A$2:$H$508,8,0) -> 4212.9527 | H196: 0.06 | I196: USD | J196: 44601.595 | K196: 44602.189 | M196: =IF(A196<>A195,M195+1,M195) -> 10029727282 | N196: =IF(M196<>M195,INDEX(CustInfo!$A$2:$A$1001,RANDBETWEEN(1,1000)),N195) -> 11201 | O196: CashOnDelivery | P196: 52936330
A197: 93827212052 | C197: 2024-01-02T14:16:06.9086921Z | D197: 2 | E197: 76891213169 | F197: =RANDBETWEEN(1,100) -> 16 | G197: =VLOOKUP(E197,PurchItem!$A$2:$H$508,8,0) -> 1750.9223 | H197: 0.04 | I197: USD | J197: 44933.595 | K197: 44935.189 | M197: =IF(A197<>A196,M196+1,M196) -> 10029727282 | N197: =IF(M197<>M196,INDEX(CustInfo!$A$2:$A$1001,RANDBETWEEN(1,1000)),N196) -> 11201 | O197: CashOnDelivery | P197: 52936331
A198: 93827212053 | C198: 2024-01-02T14:16:06.9086921Z | D198: 1 | E198: 76891213578 | F198: =RANDBETWEEN(1,100) -> 52 | G198: =VLOOKUP(E198,PurchItem!$A$2:$H$508,8,0) -> 9231.1247 | H198: 0.06 | I198: USD | J198: 45524.595 | K198: 45525.189 | M198: =IF(A198<>A197,M197+1,M197) -> 10029727283 | N198: =IF(M198<>M197,INDEX(CustInfo!$A$2:$A$1001,RANDBETWEEN(1,1000)),N197) -> 11977 | O198: CashOnDelivery | P198: 52936332
A199: 93827212053 | C199: 2024-01-02T14:16:06.9086921Z | D199: 2 | E199: 76891213245 | F199: =RANDBETWEEN(1,100) -> 1 | G199: =VLOOKUP(E199,PurchItem!$A$2:$H$508,8,0) -> 4529.342 | H199: 0.04 | I199: USD | J199: 45282.595 | K199: 45283.189 | M199: =IF(A199<>A198,M198+1,M198) -> 10029727283 | N199: =IF(M199<>M198,INDEX(CustInfo!$A$2:$A$1001,RANDBETWEEN(1,1000)),N198) -> 11977 | O199: CashOnDelivery | P199: 52936333
A200: 93827212053 | C200: 2024-01-02T14:16:06.9086921Z | D200: 3 | E200: 76891213593 | F200: =RANDBETWEEN(1,100) -> 45 | G200: =VLOOKUP(E200,PurchItem!$A$2:$H$508,8,0) -> 2737.5203 | H200: 0.04 | I200: USD | J200: 44715.595 | K200: 44719.189 | M200: =IF(A200<>A199,M199+1,M199) -> 10029727283 | N200: =IF(M200<>M199,INDEX(CustInfo!$A$2:$A$1001,RANDBETWEEN(1,1000)),N199) -> 11977 | O200: CashOnDelivery | P200: 52936334
A201: 93827212054 | C201: 2024-01-02T14:16:06.9086921Z | D201: 1 | E201: 76891213449 | F201: =RANDBETWEEN(1,100) -> 67 | G201: =VLOOKUP(E201,PurchItem!$A$2:$H$508,8,0) -> 8466.7709 | H201: 0.04 | I201: USD | J201: 44983.595 | K201: 44986.189 | M201: =IF(A201<>A200,M200+1,M200) -> 10029727284 | N201: =IF(M201<>M200,INDEX(CustInfo!$A$2:$A$1001,RANDBETWEEN(1,1000)),N200) -> 11712 | O201: CreditCard | P201: 52936335
A202: 93827212054 | C202: 2024-01-02T14:16:06.9086921Z | D202: 2 | E202: 76891213232 | F202: =RANDBETWEEN(1,100) -> 7 | G202: =VLOOKUP(E202,PurchItem!$A$2:$H$508,8,0) -> 8714.7937 | H202: 0.06 | I202: USD | J202: 45193.595 | K202: 45195.189 | M202: =IF(A202<>A201,M201+1,M201) -> 10029727284 | N202: =IF(M202<>M201,INDEX(CustInfo!$A$2:$A$1001,RANDBETWEEN(1,1000)),N201) -> 11712 | O202: CreditCard | P202: 52936336
A203: 93827212054 | C203: 2024-01-02T14:16:06.9086921Z | D203: 3 | E203: 76891213469 | F203: =RANDBETWEEN(1,100) -> 83 | G203: =VLOOKUP(E203,PurchItem!$A$2:$H$508,8,0) -> 3640.4378 | H203: 0.05 | I203: USD | J203: 44916.595 | K203: 44920.189 | M203: =IF(A203<>A202,M202+1,M202) -> 10029727284 | N203: =IF(M203<>M202,INDEX(CustInfo!$A$2:$A$1001,RANDBETWEEN(1,1000)),N202) -> 11712 | O203: CreditCard | P203: 52936337
A204: 93827212055 | C204: 2024-01-02T14:16:06.9086921Z | D204: 1 | E204: 76891213223 | F204: =RANDBETWEEN(1,100) -> 91 | G204: =VLOOKUP(E204,PurchItem!$A$2:$H$508,8,0) -> 9143.6021 | H204: 0.05 | I204: USD | J204: 44860.595 | K204: 44863.189 | M204: =IF(A204<>A203,M203+1,M203) -> 10029727285 | N204: =IF(M204<>M203,INDEX(CustInfo!$A$2:$A$1001,RANDBETWEEN(1,1000)),N203) -> 11757 | O204: DebitCard | P204: 52936338
A205: 93827212055 | C205: 2024-01-02T14:16:06.9086921Z | D205: 2 | E205: 76891213572 | F205: =RANDBETWEEN(1,100) -> 8 | G205: =VLOOKUP(E205,PurchItem!$A$2:$H$508,8,0) -> 8369.1775 | H205: 0.05 | I205: USD | J205: 45302.595 | K205: 45304.189 | M205: =IF(A205<>A204,M204+1,M204) -> 10029727285 | N205: =IF(M205<>M204,INDEX(CustInfo!$A$2:$A$1001,RANDBETWEEN(1,1000)),N204) -> 11757 | O205: DebitCard | P205: 52936339
A206: 93827212055 | C206: 2024-01-02T14:16:06.9086921Z | D206: 3 | E206: 76891213327 | F206: =RANDBETWEEN(1,100) -> 96 | G206: =VLOOKUP(E206,PurchItem!$A$2:$H$508,8,0) -> 2188.0437 | H206: 0.06 | I206: USD | J206: 44900.595 | K206: 44903.189 | M206: =IF(A206<>A205,M205+1,M205) -> 10029727285 | N206: =IF(M206<>M205,INDEX(CustInfo!$A$2:$A$1001,RANDBETWEEN(1,1000)),N205) -> 11757 | O206: DebitCard | P206: 52936340
A207: 93827212056 | C207: 2024-01-02T14:16:06.9086921Z | D207: 1 | E207: 76891213454 | F207: =RANDBETWEEN(1,100) -> 50 | G207: =VLOOKUP(E207,PurchItem!$A$2:$H$508,8,0) -> 9734.0215 | H207: 0.06 | I207: USD | J207: 44643.595 | K207: 44646.189 | M207: =IF(A207<>A206,M206+1,M206) -> 10029727286 | N207: =IF(M207<>M206,INDEX(CustInfo!$A$2:$A$1001,RANDBETWEEN(1,1000)),N206) -> 11914 | O207: CreditCard | P207: 52936341
... A319: 93827212100 | C319: 2024-01-02T14:16:06.9086921Z | D319: 1 | E319: 76891213203 | F319: =RANDBETWEEN(1,100) -> 64 | G319: =VLOOKUP(E319,PurchItem!$A$2:$H$508,8,0) -> 9569.6271 | H319: 0.06 | I319: USD | J319: 45409.595 | K319: 45412.189 | M319: =IF(A319<>A318,M318+1,M318) -> 10029727330 | N319: =IF(M319<>M318,INDEX(CustInfo!$A$2:$A$1001,RANDBETWEEN(1,1000)),N318) -> 11075 | O319: CashOnDelivery | P319: 52936453
A320: 93827212100 | C320: 2024-01-02T14:16:06.9086921Z | D320: 2 | E320: 76891213156 | F320: =RANDBETWEEN(1,100) -> 71 | G320: =VLOOKUP(E320,PurchItem!$A$2:$H$508,8,0) -> 9558.6946 | H320: 0.06 | I320: USD | J320: =RANDBETWEEN(DATE(2022,1,1),TODAY()-30)+$U$2 -> 44580 | K320: =J320+RANDBETWEEN(0,3)+$U$2 -> 44583 | M320: =IF(A320<>A319,M319+1,M319) -> 10029727330 | N320: =IF(M320<>M319,INDEX(CustInfo!$A$2:$A$1001,RANDBETWEEN(1,1000)),N319) -> 11075 | O320: CashOnDelivery | P320: 52936454
A321: 93827212100 | C321: 2024-01-02T14:16:06.9086921Z | D321: 3 | E321: 76891213334 | F321: =RANDBETWEEN(1,100) -> 12 | G321: =VLOOKUP(E321,PurchItem!$A$2:$H$508,8,0) -> 8701.4874 | H321: 0.06 | I321: USD | J321: 44774.595 | K321: 44776.189 | M321: =IF(A321<>A320,M320+1,M320) -> 10029727330 | N321: =IF(M321<>M320,INDEX(CustInfo!$A$2:$A$1001,RANDBETWEEN(1,1000)),N320) -> 11075 | O321: CashOnDelivery | P321: 52936455
A322: 93827212100 | C322: 2024-01-02T14:16:06.9086921Z | D322: 4 | E322: 76891213205 | F322: =RANDBETWEEN(1,100) -> 99 | G322: =VLOOKUP(E322,PurchItem!$A$2:$H$508,8,0) -> 1670.4986 | H322: 0.06 | I322: USD | J322: 45569.595 | K322: 45571.189 | M322: =IF(A322<>A321,M321+1,M321) -> 10029727330 | N322: =IF(M322<>M321,INDEX(CustInfo!$A$2:$A$1001,RANDBETWEEN(1,1000)),N321) -> 11075 | O322: CashOnDelivery | P322: 52936456
A323: 93827212101 | C323: 2024-01-02T14:16:06.9086921Z | D323: 1 | E323: 76891213566 | F323: =RANDBETWEEN(1,100) -> 62 | G323: =VLOOKUP(E323,PurchItem!$A$2:$H$508,8,0) -> 4496.7841 | H323: 0.04 | I323: USD | J323: 44605.595 | K323: 44609.189 | M323: =IF(A323<>A322,M322+1,M322) -> 10029727331 | N323: =IF(M323<>M322,INDEX(CustInfo!$A$2:$A$1001,RANDBETWEEN(1,1000)),N322) -> 11123 | O323: CreditCard | P323: 52936457
A324: 93827212101 | C324: 2024-01-02T14:16:06.9086921Z | D324: 2 | E324: 76891213279 | F324: =RANDBETWEEN(1,100) -> 68 | G324: =VLOOKUP(E324,PurchItem!$A$2:$H$508,8,0) -> 4031.2931 | H324: 0.05 | I324: USD | J324: 45491.595 | K324: 45493.189 | M324: =IF(A324<>A323,M323+1,M323) -> 10029727331 | N324: =IF(M324<>M323,INDEX(CustInfo!$A$2:$A$1001,RANDBETWEEN(1,1000)),N323) -> 11123 | O324: CreditCard | P324: 52936458
A325: 93827212101 | C325: 2024-01-02T14:16:06.9086921Z | D325: 3 | E325: 76891213219 | F325: =RANDBETWEEN(1,100) -> 48 | G325: =VLOOKUP(E325,PurchItem!$A$2:$H$508,8,0) -> 660.79399 | H325: 0.05 | I325: USD | J325: 45521.595 | K325: 45523.189 | M325: =IF(A325<>A324,M324+1,M324) -> 10029727331 | N325: =IF(M325<>M324,INDEX(CustInfo!$A$2:$A$1001,RANDBETWEEN(1,1000)),N324) -> 11123 | O325: CreditCard | P325: 52936459
A326: 93827212101 | C326: 2024-01-02T14:16:06.9086921Z | D326: 4 | E326: 76891213584 | F326: =RANDBETWEEN(1,100) -> 77 | G326: =VLOOKUP(E326,PurchItem!$A$2:$H$508,8,0) -> 6945.1849 | H326: 0.04 | I326: USD | J326: 45590.595 | K326: 45593.189 | M326: =IF(A326<>A325,M325+1,M325) -> 10029727331 | N326: =IF(M326<>M325,INDEX(CustInfo!$A$2:$A$1001,RANDBETWEEN(1,1000)),N325) -> 11123 | O326: CreditCard | P326: 52936460
A327: 93827212102 | C327: 2024-01-02T14:16:06.9086921Z | D327: 1 | E327: 76891213241 | F327: =RANDBETWEEN(1,100) -> 15 | G327: =VLOOKUP(E327,PurchItem!$A$2:$H$508,8,0) -> 3049.7559 | H327: 0.05 | I327: USD | J327: 45408.595 | K327: 45411.189 | M327: =IF(A327<>A326,M326+1,M326) -> 10029727332 | N327: =IF(M327<>M326,INDEX(CustInfo!$A$2:$A$1001,RANDBETWEEN(1,1000)),N326) -> 11671 | O327: CashOnDelivery | P327: 52936461
A328: 93827212102 | C328: 2024-01-02T14:16:06.9086921Z | D328: 2 | E328: 76891213637 | F328: =RANDBETWEEN(1,100) -> 69 | G328: =VLOOKUP(E328,PurchItem!$A$2:$H$508,8,0) -> 5862.4718 | H328: 0.05 | I328: USD | J328: 45202.595 | K328: 45205.189 | M328: =IF(A328<>A327,M327+1,M327) -> 10029727332 | N328: =IF(M328<>M327,INDEX(CustInfo!$A$2:$A$1001,RANDBETWEEN(1,1000)),N327) -> 11671 | O328: CashOnDelivery | P328: 52936462
A329: 93827212102 | C329: 2024-01-02T14:16:06.9086921Z | D329: 3 | E329: 76891213464 | F329: =RANDBETWEEN(1,100) -> 36 | G329: =VLOOKUP(E329,PurchItem!$A$2:$H$508,8,0) -> 3775.4439 | H329: 0.06 | I329: USD | J329: 45002.595 | K329: 45004.189 | M329: =IF(A329<>A328,M328+1,M328) -> 10029727332 | N329: =IF(M329<>M328,INDEX(CustInfo!$A$2:$A$1001,RANDBETWEEN(1,1000)),N328) -> 11671 | O329: CashOnDelivery | P329: 52936463
A330: 93827212102 | C330: 2024-01-02T14:16:06.9086921Z | D330: 4 | E330: 76891213391 | F330: =RANDBETWEEN(1,100) -> 38 | G330: =VLOOKUP(E330,PurchItem!$A$2:$H$508,8,0) -> 3029.602 | H330: 0.06 | I330: USD | J330: 45250.595 | K330: 45251.189 | M330: =IF(A330<>A329,M329+1,M329) -> 10029727332 | N330: =IF(M330<>M329,INDEX(CustInfo!$A$2:$A$1001,RANDBETWEEN(1,1000)),N329) -> 11671 | O330: CashOnDelivery | P330: 52936464
A331: 93827212103 | C331: 2024-01-02T14:16:06.9086921Z | D331: 1 | E331: 76891213470 | F331: =RANDBETWEEN(1,100) -> 62 | G331: =VLOOKUP(E331,PurchItem!$A$2:$H$508,8,0) -> 2084.2612 | H331: 0.06 | I331: USD | J331: 45401.595 | K331: 45403.189 | M331: =IF(A331<>A330,M330+1,M330) -> 10029727333 | N331: =IF(M331<>M330,INDEX(CustInfo!$A$2:$A$1001,RANDBETWEEN(1,1000)),N330) -> 11174 | O331: CreditCard | P331: 52936465
A332: 93827212104 | C332: 2024-01-02T14:16:06.9086921Z | D332: 1 | E332: 76891213294 | F332: =RANDBETWEEN(1,100) -> 14 | G332: =VLOOKUP(E332,PurchItem!$A$2:$H$508,8,0) -> 1758.1992 | H332: 0.06 | I332: USD | J332: 45421.595 | K332: 45422.189 | M332: =IF(A332<>A331,M331+1,M331) -> 10029727334 | N332: =IF(M332<>M331,INDEX(CustInfo!$A$2:$A$1001,RANDBETWEEN(1,1000)),N331) -> 11829 | O332: CreditCard | P332: 52936466
... A513: 93827212175 | C513: 2024-01-02T14:16:06.9086921Z | D513: 1 | E513: 76891213142 | F513: =RANDBETWEEN(1,100) -> 55 | G513: =VLOOKUP(E513,PurchItem!$A$2:$H$508,8,0) -> 5034.8662 | H513: 0.04 | I513: USD | J513: 45409.595 | K513: 45412.189 | M513: =IF(A513<>A512,M512+1,M512) -> 10029727405 | N513: =IF(M513<>M512,INDEX(CustInfo!$A$2:$A$1001,RANDBETWEEN(1,1000)),N512) -> 11969 | O513: CreditCard | P513: 52936647
A514: 93827212175 | C514: 2024-01-02T14:16:06.9086921Z | D514: 2 | E514: 76891213518 | F514: =RANDBETWEEN(1,100) -> 35 | G514: =VLOOKUP(E514,PurchItem!$A$2:$H$508,8,0) -> 898.75448 | H514: 0.04 | I514: USD | J514: =RANDBETWEEN(DATE(2022,1,1),TODAY()-30)+$U$2 -> 45299 | K514: =J514+RANDBETWEEN(0,3)+$U$2 -> 45301 | M514: =IF(A514<>A513,M513+1,M513) -> 10029727405 | N514: =IF(M514<>M513,INDEX(CustInfo!$A$2:$A$1001,RANDBETWEEN(1,1000)),N513) -> 11969 | O514: CreditCard | P514: 52936648
A515: 93827212176 | C515: 2024-01-02T14:16:06.9086921Z | D515: 1 | E515: 76891213479 | F515: =RANDBETWEEN(1,100) -> 15 | G515: =VLOOKUP(E515,PurchItem!$A$2:$H$508,8,0) -> 6220.909 | H515: 0.06 | I515: USD | J515: 44774.595 | K515: 44776.189 | M515: =IF(A515<>A514,M514+1,M514) -> 10029727406 | N515: =IF(M515<>M514,INDEX(CustInfo!$A$2:$A$1001,RANDBETWEEN(1,1000)),N514) -> 11641 | O515: DebitCard | P515: 52936649
A516: 93827212176 | C516: 2024-01-02T14:16:06.9086921Z | D516: 2 | E516: 76891213156 | F516: =RANDBETWEEN(1,100) -> 83 | G516: =VLOOKUP(E516,PurchItem!$A$2:$H$508,8,0) -> 9558.6946 | H516: 0.05 | I516: USD | J516: 45569.595 | K516: 45571.189 | M516: =IF(A516<>A515,M515+1,M515) -> 10029727406 | N516: =IF(M516<>M515,INDEX(CustInfo!$A$2:$A$1001,RANDBETWEEN(1,1000)),N515) -> 11641 | O516: DebitCard | P516: 52936650
A517: 93827212177 | C517: 2024-01-02T14:16:06.9086921Z | D517: 1 | E517: 76891213385 | F517: =RANDBETWEEN(1,100) -> 80 | G517: =VLOOKUP(E517,PurchItem!$A$2:$H$508,8,0) -> 6325.6133 | H517: 0.05 | I517: USD | J517: 44605.595 | K517: 44609.189 | M517: =IF(A517<>A516,M516+1,M516) -> 10029727407 | N517: =IF(M517<>M516,INDEX(CustInfo!$A$2:$A$1001,RANDBETWEEN(1,1000)),N516) -> 11610 | O517: CashOnDelivery | P517: 52936651
A518: 93827212177 | C518: 2024-01-02T14:16:06.9086921Z | D518: 2 | E518: 76891213457 | F518: =RANDBETWEEN(1,100) -> 56 | G518: =VLOOKUP(E518,PurchItem!$A$2:$H$508,8,0) -> 6617.5399 | H518: 0.05 | I518: USD | J518: 45491.595 | K518: 45493.189 | M518: =IF(A518<>A517,M517+1,M517) -> 10029727407 | N518: =IF(M518<>M517,INDEX(CustInfo!$A$2:$A$1001,RANDBETWEEN(1,1000)),N517) -> 11610 | O518: CashOnDelivery | P518: 52936652
A519: 93827212177 | C519: 2024-01-02T14:16:06.9086921Z | D519: 3 | E519: 76891213569 | F519: =RANDBETWEEN(1,100) -> 35 | G519: =VLOOKUP(E519,PurchItem!$A$2:$H$508,8,0) -> 1466.4146 | H519: 0.06 | I519: USD | J519: 45521.595 | K519: 45523.189 | M519: =IF(A519<>A518,M518+1,M518) -> 10029727407 | N519: =IF(M519<>M518,INDEX(CustInfo!$A$2:$A$1001,RANDBETWEEN(1,1000)),N518) -> 11610 | O519: CashOnDelivery | P519: 52936653
A520: 93827212178 | C520: 2024-01-02T14:16:06.9086921Z | D520: 1 | E520: 76891213182 | F520: =RANDBETWEEN(1,100) -> 56 | G520: =VLOOKUP(E520,PurchItem!$A$2:$H$508,8,0) -> 6993.4676 | H520: 0.06 | I520: USD | J520: 45590.595 | K520: 45593.189 | M520: =IF(A520<>A519,M519+1,M519) -> 10029727408 | N520: =IF(M520<>M519,INDEX(CustInfo!$A$2:$A$1001,RANDBETWEEN(1,1000)),N519) -> 11812 | O520: CreditCard | P520: 52936654
A521: 93827212178 | C521: 2024-01-02T14:16:06.9086921Z | D521: 2 | E521: 76891213606 | F521: =RANDBETWEEN(1,100) -> 29 | G521: =VLOOKUP(E521,PurchItem!$A$2:$H$508,8,0) -> 2599.1189 | H521: 0.04 | I521: USD | J521: 45408.595 | K521: 45411.189 | M521: =IF(A521<>A520,M520+1,M520) -> 10029727408 | N521: =IF(M521<>M520,INDEX(CustInfo!$A$2:$A$1001,RANDBETWEEN(1,1000)),N520) -> 11812 | O521: CreditCard | P521: 52936655
A522: 93827212179 | C522: 2024-01-02T14:16:06.9086921Z | D522: 1 | E522: 76891213403 | F522: =RANDBETWEEN(1,100) -> 81 | G522: =VLOOKUP(E522,PurchItem!$A$2:$H$508,8,0) -> 7222.6268 | H522: 0.04 | I522: USD | J522: 45202.595 | K522: 45205.189 | M522: =IF(A522<>A521,M521+1,M521) -> 10029727409 | N522: =IF(M522<>M521,INDEX(CustInfo!$A$2:$A$1001,RANDBETWEEN(1,1000)),N521) -> 11911 | O522: CreditCard | P522: 52936656
A523: 93827212179 | C523: 2024-01-02T14:16:06.9086921Z | D523: 2 | E523: 76891213354 | F523: =RANDBETWEEN(1,100) -> 83 | G523: =VLOOKUP(E523,PurchItem!$A$2:$H$508,8,0) -> 9590.7052 | H523: 0.05 | I523: USD | J523: 45002.595 | K523: 45004.189 | M523: =IF(A523<>A522,M522+1,M522) -> 10029727409 | N523: =IF(M523<>M522,INDEX(CustInfo!$A$2:$A$1001,RANDBETWEEN(1,1000)),N522) -> 11911 | O523: CreditCard | P523: 52936657
A524: 93827212180 | C524: 2024-01-02T14:16:06.9086921Z | D524: 1 | E524: 76891213183 | F524: =RANDBETWEEN(1,100) -> 39 | G524: =VLOOKUP(E524,PurchItem!$A$2:$H$508,8,0) -> 4515.178 | H524: 0.04 | I524: USD | J524: 45250.595 | K524: 45251.189 | M524: =IF(A524<>A523,M523+1,M523) -> 10029727410 | N524: =IF(M524<>M523,INDEX(CustInfo!$A$2:$A$1001,RANDBETWEEN(1,1000)),N523) -> 11644 | O524: DebitCard | P524: 52936658
A525: 93827212180 | C525: 2024-01-02T14:16:06.9086921Z | D525: 2 | E525: 76891213163 | F525: =RANDBETWEEN(1,100) -> 22 | G525: =VLOOKUP(E525,PurchItem!$A$2:$H$508,8,0) -> 8353.8076 | H525: 0.06 | I525: USD | J525: 45401.595 | K525: 45403.189 | M525: =IF(A525<>A524,M524+1,M524) -> 10029727410 | N525: =IF(M525<>M524,INDEX(CustInfo!$A$2:$A$1001,RANDBETWEEN(1,1000)),N524) -> 11644 | O525: DebitCard | P525: 52936659
A526: 93827212180 | C526: 2024-01-02T14:16:06.9086921Z | D526: 3 | E526: 76891213178 | F526: =RANDBETWEEN(1,100) -> 99 | G526: =VLOOKUP(E526,PurchItem!$A$2:$H$508,8,0) -> 2256.6727 | H526: 0.04 | I526: USD | J526: 45421.595 | K526: 45422.189 | M526: =IF(A526<>A525,M525+1,M525) -> 10029727410 | N526: =IF(M526<>M525,INDEX(CustInfo!$A$2:$A$1001,RANDBETWEEN(1,1000)),N525) -> 11644 | O526: DebitCard | P526: 52936660
... A707: 93827212250 | C707: 2024-01-02T14:16:06.9086921Z | D707: 1 | E707: 76891213597 | F707: =RANDBETWEEN(1,100) -> 27 | G707: =VLOOKUP(E707,PurchItem!$A$2:$H$508,8,0) -> 6407.6591 | H707: 0.04 | I707: USD | J707: 45409.595 | K707: 45412.189 | M707: =IF(A707<>A706,M706+1,M706) -> 10029727480 | N707: =IF(M707<>M706,INDEX(CustInfo!$A$2:$A$1001,RANDBETWEEN(1,1000)),N706) -> 11565 | O707: CashOnDelivery | P707: 52936841
A708: 93827212250 | C708: 2024-01-02T14:16:06.9086921Z | D708: 2 | E708: 76891213253 | F708: =RANDBETWEEN(1,100) -> 61 | G708: =VLOOKUP(E708,PurchItem!$A$2:$H$508,8,0) -> 2205.8632 | H708: 0.05 | I708: USD | J708: =RANDBETWEEN(DATE(2022,1,1),TODAY()-30)+$U$2 -> 44767 | K708: =J708+RANDBETWEEN(0,3)+$U$2 -> 44770 | M708: =IF(A708<>A707,M707+1,M707) -> 10029727480 | N708: =IF(M708<>M707,INDEX(CustInfo!$A$2:$A$1001,RANDBETWEEN(1,1000)),N707) -> 11565 | O708: CashOnDelivery | P708: 52936842
A709: 93827212251 | C709: 2024-01-02T14:16:06.9086921Z | D709: 1 | E709: 76891213182 | F709: =RANDBETWEEN(1,100) -> 27 | G709: =VLOOKUP(E709,PurchItem!$A$2:$H$508,8,0) -> 6993.4676 | H709: 0.04 | I709: USD | J709: 44774.595 | K709: 44776.189 | M709: =IF(A709<>A708,M708+1,M708) -> 10029727481 | N709: =IF(M709<>M708,INDEX(CustInfo!$A$2:$A$1001,RANDBETWEEN(1,1000)),N708) -> 11043 | O709: CashOnDelivery | P709: 52936843
A710: 93827212251 | C710: 2024-01-02T14:16:06.9086921Z | D710: 2 | E710: 76891213278 | F710: =RANDBETWEEN(1,100) -> 14 | G710: =VLOOKUP(E710,PurchItem!$A$2:$H$508,8,0) -> 5013.6146 | H710: 0.04 | I710: USD | J710: 45569.595 | K710: 45571.189 | M710: =IF(A710<>A709,M709+1,M709) -> 10029727481 | N710: =IF(M710<>M709,INDEX(CustInfo!$A$2:$A$1001,RANDBETWEEN(1,1000)),N709) -> 11043 | O710: CashOnDelivery | P710: 52936844
A711: 93827212251 | C711: 2024-01-02T14:16:06.9086921Z | D711: 3 | E711: 76891213491 | F711: =RANDBETWEEN(1,100) -> 45 | G711: =VLOOKUP(E711,PurchItem!$A$2:$H$508,8,0) -> 2320.7084 | H711: 0.04 | I711: USD | J711: 44605.595 | K711: 44609.189 | M711: =IF(A711<>A710,M710+1,M710) -> 10029727481 | N711: =IF(M711<>M710,INDEX(CustInfo!$A$2:$A$1001,RANDBETWEEN(1,1000)),N710) -> 11043 | O711: CashOnDelivery | P711: 52936845
A712: 93827212251 | C712: 2024-01-02T14:16:06.9086921Z | D712: 4 | E712: 76891213165 | F712: =RANDBETWEEN(1,100) -> 50 | G712: =VLOOKUP(E712,PurchItem!$A$2:$H$508,8,0) -> 782.2884 | H712: 0.06 | I712: USD | J712: 45491.595 | K712: 45493.189 | M712: =IF(A712<>A711,M711+1,M711) -> 10029727481 | N712: =IF(M712<>M711,INDEX(CustInfo!$A$2:$A$1001,RANDBETWEEN(1,1000)),N711) -> 11043 | O712: CashOnDelivery | P712: 52936846
A713: 93827212252 | C713: 2024-01-02T14:16:06.9086921Z | D713: 1 | E713: 76891213626 | F713: =RANDBETWEEN(1,100) -> 93 | G713: =VLOOKUP(E713,PurchItem!$A$2:$H$508,8,0) -> 5785.3223 | H713: 0.06 | I713: USD | J713: 45521.595 | K713: 45523.189 | M713: =IF(A713<>A712,M712+1,M712) -> 10029727482 | N713: =IF(M713<>M712,INDEX(CustInfo!$A$2:$A$1001,RANDBETWEEN(1,1000)),N712) -> 11852 | O713: DebitCard | P713: 52936847
A714: 93827212252 | C714: 2024-01-02T14:16:06.9086921Z | D714: 2 | E714: 76891213169 | F714: =RANDBETWEEN(1,100) -> 35 | G714: =VLOOKUP(E714,PurchItem!$A$2:$H$508,8,0) -> 1750.9223 | H714: 0.04 | I714: USD | J714: 45590.595 | K714: 45593.189 | M714: =IF(A714<>A713,M713+1,M713) -> 10029727482 | N714: =IF(M714<>M713,INDEX(CustInfo!$A$2:$A$1001,RANDBETWEEN(1,1000)),N713) -> 11852 | O714: DebitCard | P714: 52936848
A715: 93827212252 | C715: 2024-01-02T14:16:06.9086921Z | D715: 3 | E715: 76891213376 | F715: =RANDBETWEEN(1,100) -> 88 | G715: =VLOOKUP(E715,PurchItem!$A$2:$H$508,8,0) -> 7089.7518 | H715: 0.05 | I715: USD | J715: 45408.595 | K715: 45411.189 | M715: =IF(A715<>A714,M714+1,M714) -> 10029727482 | N715: =IF(M715<>M714,INDEX(CustInfo!$A$2:$A$1001,RANDBETWEEN(1,1000)),N714) -> 11852 | O715: DebitCard | P715: 52936849
A716: 93827212253 | C716: 2024-01-02T14:16:06.9086921Z | D716: 1 | E716: 76891213445 | F716: =RANDBETWEEN(1,100) -> 42 | G716: =VLOOKUP(E716,PurchItem!$A$2:$H$508,8,0) -> 4377.3478 | H716: 0.04 | I716: USD | J716: 45202.595 | K716: 45205.189 | M716: =IF(A716<>A715,M715+1,M715) -> 10029727483 | N716: =IF(M716<>M715,INDEX(CustInfo!$A$2:$A$1001,RANDBETWEEN(1,1000)),N715) -> 11704 | O716: CashOnDelivery | P716: 52936850
A717: 93827212253 | C717: 2024-01-02T14:16:06.9086921Z | D717: 2 | E717: 76891213484 | F717: =RANDBETWEEN(1,100) -> 94 | G717: =VLOOKUP(E717,PurchItem!$A$2:$H$508,8,0) -> 6278.4735 | H717: 0.06 | I717: USD | J717: 45002.595 | K717: 45004.189 | M717: =IF(A717<>A716,M716+1,M716) -> 10029727483 | N717: =IF(M717<>M716,INDEX(CustInfo!$A$2:$A$1001,RANDBETWEEN(1,1000)),N716) -> 11704 | O717: CashOnDelivery | P717: 52936851
A718: 93827212254 | C718: 2024-01-02T14:16:06.9086921Z | D718: 1 | E718: 76891213274 | F718: =RANDBETWEEN(1,100) -> 69 | G718: =VLOOKUP(E718,PurchItem!$A$2:$H$508,8,0) -> 6244.6026 | H718: 0.06 | I718: USD | J718: 45250.595 | K718: 45251.189 | M718: =IF(A718<>A717,M717+1,M717) -> 10029727484 | N718: =IF(M718<>M717,INDEX(CustInfo!$A$2:$A$1001,RANDBETWEEN(1,1000)),N717) -> 11272 | O718: CashOnDelivery | P718: 52936852
A719: 93827212255 | C719: 2024-01-02T14:16:06.9086921Z | D719: 1 | E719: 76891213260 | F719: =RANDBETWEEN(1,100) -> 59 | G719: =VLOOKUP(E719,PurchItem!$A$2:$H$508,8,0) -> 6861.1197 | H719: 0.05 | I719: USD | J719: 45401.595 | K719: 45403.189 | M719: =IF(A719<>A718,M718+1,M718) -> 10029727485 | N719: =IF(M719<>M718,INDEX(CustInfo!$A$2:$A$1001,RANDBETWEEN(1,1000)),N718) -> 11636 | O719: CashOnDelivery | P719: 52936853
A720: 93827212255 | C720: 2024-01-02T14:16:06.9086921Z | D720: 2 | E720: 76891213627 | F720: =RANDBETWEEN(1,100) -> 9 | G720: =VLOOKUP(E720,PurchItem!$A$2:$H$508,8,0) -> 7533.0368 | H720: 0.06 | I720: USD | J720: 45421.595 | K720: 45422.189 | M720: =IF(A720<>A719,M719+1,M719) -> 10029727485 | N720: =IF(M720<>M719,INDEX(CustInfo!$A$2:$A$1001,RANDBETWEEN(1,1000)),N719) -> 11636 | O720: CashOnDelivery | P720: 52936854
... A901: 93827212326 | C901: 2024-01-02T14:16:06.9086921Z | D901: 3 | E901: 76891213271 | F901: =RANDBETWEEN(1,100) -> 25 | G901: =VLOOKUP(E901,PurchItem!$A$2:$H$508,8,0) -> 2763.8336 | H901: 0.05 | I901: USD | J901: 45409.595 | K901: 45412.189 | M901: =IF(A901<>A900,M900+1,M900) -> 10029727556 | N901: =IF(M901<>M900,INDEX(CustInfo!$A$2:$A$1001,RANDBETWEEN(1,1000)),N900) -> 11074 | O901: DebitCard | P901: 52937035
A902: 93827212326 | C902: 2024-01-02T14:16:06.9086921Z | D902: 4 | E902: 76891213434 | F902: =RANDBETWEEN(1,100) -> 5 | G902: =VLOOKUP(E902,PurchItem!$A$2:$H$508,8,0) -> 1035.2794 | H902: 0.04 | I902: USD | J902: =RANDBETWEEN(DATE(2022,1,1),TODAY()-30)+$U$2 -> 45022 | K902: =J902+RANDBETWEEN(0,3)+$U$2 -> 45022 | M902: =IF(A902<>A901,M901+1,M901) -> 10029727556 | N902: =IF(M902<>M901,INDEX(CustInfo!$A$2:$A$1001,RANDBETWEEN(1,1000)),N901) -> 11074 | O902: DebitCard | P902: 52937036
A903: 93827212327 | C903: 2024-01-02T14:16:06.9086921Z | D903: 1 | E903: 76891213232 | F903: =RANDBETWEEN(1,100) -> 39 | G903: =VLOOKUP(E903,PurchItem!$A$2:$H$508,8,0) -> 8714.7937 | H903: 0.05 | I903: USD | J903: 44774.595 | K903: 44776.189 | M903: =IF(A903<>A902,M902+1,M902) -> 10029727557 | N903: =IF(M903<>M902,INDEX(CustInfo!$A$2:$A$1001,RANDBETWEEN(1,1000)),N902) -> 11985 | O903: DebitCard | P903: 52937037
A904: 93827212327 | C904: 2024-01-02T14:16:06.9086921Z | D904: 2 | E904: 76891213274 | F904: =RANDBETWEEN(1,100) -> 25 | G904: =VLOOKUP(E904,PurchItem!$A$2:$H$508,8,0) -> 6244.6026 | H904: 0.06 | I904: USD | J904: 45569.595 | K904: 45571.189 | M904: =IF(A904<>A903,M903+1,M903) -> 10029727557 | N904: =IF(M904<>M903,INDEX(CustInfo!$A$2:$A$1001,RANDBETWEEN(1,1000)),N903) -> 11985 | O904: DebitCard | P904: 52937038
A905: 93827212327 | C905: 2024-01-02T14:16:06.9086921Z | D905: 3 | E905: 76891213186 | F905: =RANDBETWEEN(1,100) -> 90 | G905: =VLOOKUP(E905,PurchItem!$A$2:$H$508,8,0) -> 9814.0625 | H905: 0.05 | I905: USD | J905: 44605.595 | K905: 44609.189 | M905: =IF(A905<>A904,M904+1,M904) -> 10029727557 | N905: =IF(M905<>M904,INDEX(CustInfo!$A$2:$A$1001,RANDBETWEEN(1,1000)),N904) -> 11985 | O905: DebitCard | P905: 52937039
A906: 93827212328 | C906: 2024-01-02T14:16:06.9086921Z | D906: 1 | E906: 76891213382 | F906: =RANDBETWEEN(1,100) -> 29 | G906: =VLOOKUP(E906,PurchItem!$A$2:$H$508,8,0) -> 777.90611 | H906: 0.06 | I906: USD | J906: 45491.595 | K906: 45493.189 | M906: =IF(A906<>A905,M905+1,M905) -> 10029727558 | N906: =IF(M906<>M905,INDEX(CustInfo!$A$2:$A$1001,RANDBETWEEN(1,1000)),N905) -> 11903 | O906: CreditCard | P906: 52937040
A907: 93827212328 | C907: 2024-01-02T14:16:06.9086921Z | D907: 2 | E907: 76891213192 | F907: =RANDBETWEEN(1,100) -> 81 | G907: =VLOOKUP(E907,PurchItem!$A$2:$H$508,8,0) -> 6234.1103 | H907: 0.05 | I907: USD | J907: 45521.595 | K907: 45523.189 | M907: =IF(A907<>A906,M906+1,M906) -> 10029727558 | N907: =IF(M907<>M906,INDEX(CustInfo!$A$2:$A$1001,RANDBETWEEN(1,1000)),N906) -> 11903 | O907: CreditCard | P907: 52937041
A908: 93827212328 | C908: 2024-01-02T14:16:06.9086921Z | D908: 3 | E908: 76891213433 | F908: =RANDBETWEEN(1,100) -> 15 | G908: =VLOOKUP(E908,PurchItem!$A$2:$H$508,8,0) -> 8137.8051 | H908: 0.05 | I908: USD | J908: 45590.595 | K908: 45593.189 | M908: =IF(A908<>A907,M907+1,M907) -> 10029727558 | N908: =IF(M908<>M907,INDEX(CustInfo!$A$2:$A$1001,RANDBETWEEN(1,1000)),N907) -> 11903 | O908: CreditCard | P908: 52937042
A909: 93827212329 | C909: 2024-01-02T14:16:06.9086921Z | D909: 1 | E909: 76891213195 | F909: =RANDBETWEEN(1,100) -> 60 | G909: =VLOOKUP(E909,PurchItem!$A$2:$H$508,8,0) -> 2949.5166 | H909: 0.04 | I909: USD | J909: 45408.595 | K909: 45411.189 | M909: =IF(A909<>A908,M908+1,M908) -> 10029727559 | N909: =IF(M909<>M908,INDEX(CustInfo!$A$2:$A$1001,RANDBETWEEN(1,1000)),N908) -> 11891 | O909: DebitCard | P909: 52937043
A910: 93827212329 | C910: 2024-01-02T14:16:06.9086921Z | D910: 2 | E910: 76891213262 | F910: =RANDBETWEEN(1,100) -> 16 | G910: =VLOOKUP(E910,PurchItem!$A$2:$H$508,8,0) -> 3130.1413 | H910: 0.05 | I910: USD | J910: 45202.595 | K910: 45205.189 | M910: =IF(A910<>A909,M909+1,M909) -> 10029727559 | N910: =IF(M910<>M909,INDEX(CustInfo!$A$2:$A$1001,RANDBETWEEN(1,1000)),N909) -> 11891 | O910: DebitCard | P910: 52937044
A911: 93827212329 | C911: 2024-01-02T14:16:06.9086921Z | D911: 3 | E911: 76891213485 | F911: =RANDBETWEEN(1,100) -> 98 | G911: =VLOOKUP(E911,PurchItem!$A$2:$H$508,8,0) -> 2807.3759 | H911: 0.04 | I911: USD | J911: 45002.595 | K911: 45004.189 | M911: =IF(A911<>A910,M910+1,M910) -> 10029727559 | N911: =IF(M911<>M910,INDEX(CustInfo!$A$2:$A$1001,RANDBETWEEN(1,1000)),N910) -> 11891 | O911: DebitCard | P911: 52937045
A912: 93827212329 | C912: 2024-01-02T14:16:06.9086921Z | D912: 4 | E912: 76891213348 | F912: =RANDBETWEEN(1,100) -> 77 | G912: =VLOOKUP(E912,PurchItem!$A$2:$H$508,8,0) -> 6169.984 | H912: 0.06 | I912: USD | J912: 45250.595 | K912: 45251.189 | M912: =IF(A912<>A911,M911+1,M911) -> 10029727559 | N912: =IF(M912<>M911,INDEX(CustInfo!$A$2:$A$1001,RANDBETWEEN(1,1000)),N911) -> 11891 | O912: DebitCard | P912: 52937046
A913: 93827212330 | C913: 2024-01-02T14:16:06.9086921Z | D913: 1 | E913: 76891213396 | F913: =RANDBETWEEN(1,100) -> 14 | G913: =VLOOKUP(E913,PurchItem!$A$2:$H$508,8,0) -> 6179.0714 | H913: 0.06 | I913: USD | J913: 45401.595 | K913: 45403.189 | M913: =IF(A913<>A912,M912+1,M912) -> 10029727560 | N913: =IF(M913<>M912,INDEX(CustInfo!$A$2:$A$1001,RANDBETWEEN(1,1000)),N912) -> 11551 | O913: CreditCard | P913: 52937047
A914: 93827212330 | C914: 2024-01-02T14:16:06.9086921Z | D914: 2 | E914: 76891213516 | F914: =RANDBETWEEN(1,100) -> 56 | G914: =VLOOKUP(E914,PurchItem!$A$2:$H$508,8,0) -> 6085.3231 | H914: 0.06 | I914: USD | J914: 45421.595 | K914: 45422.189 | M914: =IF(A914<>A913,M913+1,M913) -> 10029727560 | N914: =IF(M914<>M913,INDEX(CustInfo!$A$2:$A$1001,RANDBETWEEN(1,1000)),N913) -> 11551 | O914: CreditCard | P914: 52937048
... A1095: 93827212400 | C1095: 2024-01-02T14:16:06.9086921Z | D1095: 1 | E1095: 76891213502 | F1095: =RANDBETWEEN(1,100) -> 100 | G1095: =VLOOKUP(E1095,PurchItem!$A$2:$H$508,8,0) -> 7081.1969 | H1095: 0.06 | I1095: USD | J1095: 45409.595 | K1095: 45412.189 | M1095: =IF(A1095<>A1094,M1094+1,M1094) -> 10029727630 | N1095: =IF(M1095<>M1094,INDEX(CustInfo!$A$2:$A$1001,RANDBETWEEN(1,1000)),N1094) -> 11001 | O1095: CreditCard | P1095: 52937229
A1096: 93827212401 | C1096: 2024-01-02T14:16:06.9086921Z | D1096: 1 | E1096: 76891213585 | F1096: =RANDBETWEEN(1,100) -> 49 | G1096: =VLOOKUP(E1096,PurchItem!$A$2:$H$508,8,0) -> 7205.2406 | H1096: 0.06 | I1096: USD | J1096: =RANDBETWEEN(DATE(2022,1,1),TODAY()-30)+$U$2 -> 45646 | K1096: =J1096+RANDBETWEEN(0,3)+$U$2 -> 45649 | M1096: =IF(A1096<>A1095,M1095+1,M1095) -> 10029727631 | N1096: =IF(M1096<>M1095,INDEX(CustInfo!$A$2:$A$1001,RANDBETWEEN(1,1000)),N1095) -> 11786 | O1096: DebitCard | P1096: 52937230
A1097: 93827212401 | C1097: 2024-01-02T14:16:06.9086921Z | D1097: 2 | E1097: 76891213386 | F1097: =RANDBETWEEN(1,100) -> 58 | G1097: =VLOOKUP(E1097,PurchItem!$A$2:$H$508,8,0) -> 8452.4983 | H1097: 0.05 | I1097: USD | J1097: 44774.595 | K1097: 44776.189 | M1097: =IF(A1097<>A1096,M1096+1,M1096) -> 10029727631 | N1097: =IF(M1097<>M1096,INDEX(CustInfo!$A$2:$A$1001,RANDBETWEEN(1,1000)),N1096) -> 11786 | O1097: DebitCard | P1097: 52937231
...

Sheet factsalesorderline
B1: Table | C1: JoinKey | D1: Table | E1: JoinKey
B3: salesorderline | C3: CurrencyCode | D3: bronze.currency | E3: Code
B4: salesorderline | C4: PaymentTypeDesc | D4: silver.dimpaymenttypes | E4: PaymentTypeDesc
B5: promotable
B8: ColumnsNeeded | C8: If name is blank, retain the original column name
B10: Table | C10: Column | D10: Logic | E10: Name | F10: Comments
B11: salesorderline | C11: SalesOrderNumber
B12: salesorderline | C12: SalesOrderLine
B13: salesorderline | C13: LastProcessedChange_DateTime
B14: salesorderline | C14: DataLakeModified_DateTime | D14: ConvertToCST
B15: salesorderline | C15: ItemId
B16: salesorderline | C16: Qty
B17: salesorderline | C17: Price
C18: TotalAmount | D18: Qty * Price
C19: TotalAmountWithDiscount | F19: Apply the discount as per applicable promotion
B20: salesorderline | C20: VatPercentage
C21: VatAmount | D21: TotalAmountWithDiscount * VatPercentage
C22: TotalOrderAmount | D22: TotalAmountWithDiscount + VatAmount
B23: currency | C23: CurrencyId
B24: salesorderline | C24: BookDate | D24: ConvertToCST
B25: salesorderline | C25: BookDateKey | D25: Convert to Int
B26: salesorderline | C26: ShippedDate | D26: ConvertToCST
B27: salesorderline | C27: ShippedDateKey | D27: Convert to Int
B28: salesorderline | C28: DeliveredDate | D28: ConvertToCST
B29: salesorderline | C29: DeliveredKey | D29: Convert to Int
B30: salesorderline | C30: TrackingNumber
B31: salesorderline | C31: CustId
B32: silver.dimpaymenttypes | C32: PaymentTypeId
B33: promotable | C33: PromotionId
B34: salesorderline | C34: RecordId | E34: SalesOrderLineRecordId

Sheet dimpaymentTypes
A1: Tables | B1: SalesOrderLine
A4: ColumnsNeeded | B4: If name is blank, retain the original column name
A6: Table | B6: Column | C6: Logic | D6: Name | E6: Comments
B7: PaymentTypeId | E7: Generate incremental and sequential ids starting from 1 for each row
A8: SalesOrderLine | B8: PaymentTypeDesc

Sheet CustInfo
A1: CustomerId | B1: LastProcessedChange_DateTime | C1: DataLakeModified_DateTime | D1: CustomerName | E1: Email | F1: Phone | G1: Address | H1: City | I1: State | J1: Country | K1: ZipCode | L1: Region | M1: SignupDate | N1: RecordId
A2: 11000 | C2: 2024-01-02T14:16:06.9086921Z | D2: Jon Yang | E2: jon24@gmail.com | F2: 1 (11) 500 555-0162 | G2: 3761 N. 14th St | J2: United States | N2: 59251632
A3: 11001 | C3: 2024-01-02T14:16:06.9086921Z | D3: Eugene Huang | E3: eugene10@gmail.com | F3: 1 (11) 500 555-0110 | G3: 2243 W St. | J3: United States | N3: 59251633
A4: 11002 | C4: 2024-01-02T14:16:06.9086921Z | D4: Ruben Torres | E4: ruben35@gmail.com | F4: 1 (11) 500 555-0184 | G4: 5844 Linden Land | J4: United States | N4: 59251634
A5: 11003 | C5: 2024-01-02T14:16:06.9086921Z | D5: Christy Zhu | E5: christy12@gmail.com | F5: 1 (11) 500 555-0162 | G5: 1825 Village Pl. | J5: United States | N5: 59251635
A6: 11004 | C6: 2024-01-02T14:16:06.9086921Z | D6: Elizabeth Johnson | E6: elizabeth5@gmail.com | F6: 1 (11) 500 555-0131 | G6: 7553 Harness Circle | J6: United States | N6: 59251636
A7: 11005 | C7: 2024-01-02T14:16:06.9086921Z | D7: Julio Ruiz | E7: julio1@gmail.com | F7: 1 (11) 500 555-0151 | G7: 7305 Humphrey Drive | J7: United States | N7: 59251637
A8: 11006 | C8: 2024-01-02T14:16:06.9086921Z | D8: Janet Alvarez | E8: janet9@gmail.com | F8: 1 (11) 500 555-0184 | G8: 2612 Berry Dr | J8: United States | N8: 59251638
A9: 11007 | C9: 2024-01-02T14:16:06.9086921Z | D9: Marco Mehta | E9: marco14@gmail.com | F9: 1 (11) 500 555-0126 | G9: 942 Brook Street | J9: United States | N9: 59251639
A10: 11008 | C10: 2024-01-02T14:16:06.9086921Z | D10: Rob Verhoff | E10: rob4@gmail.com | F10: 1 (11) 500 555-0164 | G10: 624 Peabody Road | J10: United States | N10: 59251640
A11: 11009 | C11: 2024-01-02T14:16:06.9086921Z | D11: Shannon Carlson | E11: shannon38@gmail.com | F11: 1 (11) 500 555-0110 | G11: 3839 Northgate Road | J11: United States | N11: 59251641
A12: 11010 | C12: 2024-01-02T14:16:06.9086921Z | D12: Jacquelyn Suarez | E12: jacquelyn20@gmail.com | F12: 1 (11) 500 555-0169 | G12: 7800 Corrinne Court | J12: United States | N12: 59251642
A13: 11011 | C13: 2024-01-02T14:16:06.9086921Z | D13: Curtis Lu | E13: curtis9@gmail.com | F13: 1 (11) 500 555-0117 | G13: 1224 Shoenic | J13: United States | N13: 59251643
... A242: 11240 | C242: 2024-01-02T14:16:06.9086921Z | D242: Anne Hernandez | E242: anne4@gmail.com | F242: 1 (11) 500 555-0119 | G242: 76 Woodcrest Dr. | J242: United States | N242: 59251872
A243: 11241 | C243: 2024-01-02T14:16:06.9086921Z | D243: Lisa Cai | E243: lisa24@gmail.com | F243: 1 (11) 500 555-0125 | G243: 102 | H243: rue de Berri | J243: United States | N243: 59251873
A244: 11242 | C244: 2024-01-02T14:16:06.9086921Z | D244: Larry Munoz | E244: larry9@gmail.com | F244: 1 (11) 500 555-0193 | G244: Midi-Couleurs | J244: United States | N244: 59251874
A245: 11243 | C245: 2024-01-02T14:16:06.9086921Z | D245: Robin Alvarez | E245: robin2@gmail.com | F245: 1 (11) 500 555-0198 | G245: 4086 Emmons Canyon Lane | J245: United States | N245: 59251875
A246: 11244 | C246: 2024-01-02T14:16:06.9086921Z | D246: Alexis Coleman | E246: alexis28@gmail.com | F246: 1 (11) 500 555-0115 | G246: 7140 Camelback Road | J246: United States | N246: 59251876
A247: 11245 | C247: 2024-01-02T14:16:06.9086921Z | D247: Ricky Vazquez | E247: ricky15@gmail.com | F247: 1 (11) 500 555-0147 | G247: Roßstr 9928 | J247: United States | N247: 59251877
A248: 11246 | C248: 2024-01-02T14:16:06.9086921Z | D248: Latasha Rubio | E248: latasha21@gmail.com | F248: 1 (11) 500 555-0178 | G248: Alderstr 7690 | J248: United States | N248: 59251878
A249: 11247 | C249: 2024-01-02T14:16:06.9086921Z | D249: Claudia Zhou | E249: claudia7@gmail.com | F249: 1 (11) 500 555-0116 | G249: 6516 Beauer Lane | J249: United States | N249: 59251879
A250: 11248 | C250: 2024-01-02T14:16:06.9086921Z | D250: Tristan Alexander | E250: tristan19@gmail.com | F250: 1 (11) 500 555-0124 | G250: 88 | H250: avenue des Champs-Elysées | J250: United States | N250: 59251880
A251: 11249 | C251: 2024-01-02T14:16:06.9086921Z | D251: Cindy Patel | E251: cindy3@gmail.com | F251: 1 (11) 500 555-0149 | G251: Essener Straße 123 | J251: United States | N251: 59251881
A252: 11250 | C252: 2024-01-02T14:16:06.9086921Z | D252: Shannon Liu | E252: shannon4@gmail.com | F252: 1 (11) 500 555-0119 | G252: 4185 Keywood Ct. | J252: United States | N252: 59251882
A253: 11251 | C253: 2024-01-02T14:16:06.9086921Z | D253: Xavier Long | E253: xavier51@gmail.com | F253: 243-555-0114 | G253: 9245 Dantley Way | J253: United States | N253: 59251883
A254: 11252 | C254: 2024-01-02T14:16:06.9086921Z | D254: Nicholas Thompson | E254: nicholas16@gmail.com | F254: 377-555-0147 | G254: 504 O St. | J254: United States | N254: 59251884
A255: 11253 | C255: 2024-01-02T14:16:06.9086921Z | D255: José Hernandez | E255: josé54@gmail.com | F255: 712-555-0130 | G255: 5703 Donald Dr. | J255: United States | N255: 59251885
A256: 11254 | C256: 2024-01-02T14:16:06.9086921Z | D256: Johnathan Vance | E256: johnathan5@gmail.com | F256: 494-555-0166 | G256: 9430 Versailles Pl | J256: United States | N256: 59251886
A257: 11255 | C257: 2024-01-02T14:16:06.9086921Z | D257: Colin Lin | E257: colin8@gmail.com | F257: 599-555-0132 | G257: 6083 San Jose | J257: United States | N257: 59251887
A258: 11256 | C258: 2024-01-02T14:16:06.9086921Z | D258: Katelyn Hernandez | E258: katelyn42@gmail.com | F258: 249-555-0116 | G258: 7496 Deerfield Dr. | J258: United States | N258: 59251888
A259: 11257 | C259: 2024-01-02T14:16:06.9086921Z | D259: Jacqueline Powell | E259: jacqueline9@gmail.com | F259: 796-555-0111 | G259: 4076 Northwood Dr | J259: United States | N259: 59251889
A260: 11258 | C260: 2024-01-02T14:16:06.9086921Z | D260: Xavier Hill | E260: xavier26@gmail.com | F260: 559-555-0149 | G260: 2707 Virgil Street | J260: United States | N260: 59251890
A261: 11259 | C261: 2024-01-02T14:16:06.9086921Z | D261: Victoria Stewart | E261: victoria24@gmail.com | F261: 230-555-0139 | G261: 3623 Barquentine Court | J261: United States | N261: 59251891
A262: 11260 | C262: 2024-01-02T14:16:06.9086921Z | D262: Katelyn Kelly | E262: katelyn1@gmail.com | F262: 507-555-0132 | G262: 7085 Solano Drive | J262: United States | N262: 59251892
... A337: 11335 | C337: 2024-01-02T14:16:06.9086921Z | D337: Carla Raman | E337: carla14@gmail.com | F337: 1 (11) 500 555-0124 | G337: Winterfeldtstr 255 | J337: United States | N337: 59251967
A338: 11336 | C338: 2024-01-02T14:16:06.9086921Z | D338: Shaun Raji | E338: shaun21@gmail.com | F338: 1 (11) 500 555-0122 | G338: 44 | H338: rue du Départ | J338: United States | N338: 59251968
A339: 11337 | C339: 2024-01-02T14:16:06.9086921Z | D339: Jerome Romero | E339: jerome7@gmail.com | F339: 1 (11) 500 555-0112 | G339: 7289 Brookview Dr. | J339: United States | N339: 59251969
A340: 11338 | C340: 2024-01-02T14:16:06.9086921Z | D340: Frank Navarro | E340: frank17@gmail.com | F340: 1 (11) 500 555-0139 | G340: Buergermeister-ulrich-str 2987 | J340: United States | N340: 59251970
A341: 11339 | C341: 2024-01-02T14:16:06.9086921Z | D341: Dennis She | E341: dennis25@gmail.com | F341: 1 (11) 500 555-0141 | G341: 828 | H341: rue de Berri | J341: United States | N341: 59251971
A342: 11340 | C342: 2024-01-02T14:16:06.9086921Z | D342: Melody Munoz | E342: melody8@gmail.com | F342: 1 (11) 500 555-0147 | G342: 9 | H342: avenue Reille | J342: United States | N342: 59251972
A343: 11341 | C343: 2024-01-02T14:16:06.9086921Z | D343: Randy Zeng | E343: randy24@gmail.com | F343: 1 (11) 500 555-0144 | G343: 2334 Brandywine Way | J343: United States | N343: 59251973
A344: 11342 | C344: 2024-01-02T14:16:06.9086921Z | D344: Marshall Wang | E344: marshall0@gmail.com | F344: 1 (11) 500 555-0161 | G344: 68062 | H344: rue des Grands Champs | J344: United States | N344: 59251974
A345: 11343 | C345: 2024-01-02T14:16:06.9086921Z | D345: Arthur Carlson | E345: arthur41@gmail.com | F345: 1 (11) 500 555-0166 | G345: 6507 Fieldcrest Dr. | J345: United States | N345: 59251975
A346: 11344 | C346: 2024-01-02T14:16:06.9086921Z | D346: Jessie Jimenez | E346: jessie3@gmail.com | F346: 1 (11) 500 555-0193 | G346: 5723 C Wharton Way | J346: United States | N346: 59251976
A347: 11345 | C347: 2024-01-02T14:16:06.9086921Z | D347: Robin Ramos | E347: robin13@gmail.com | F347: 1 (11) 500 555-0111 | G347: 6 | H347: rue de l´Esplanade | J347: United States | N347: 59251977
A348: 11346 | C348: 2024-01-02T14:16:06.9086921Z | D348: Deanna Gutierrez | E348: deanna37@gmail.com | F348: 1 (11) 500 555-0112 | G348: Attaché de Presse | J348: United States | N348: 59251978
A349: 11347 | C349: 2024-01-02T14:16:06.9086921Z | D349: Roy Navarro | E349: roy30@gmail.com | F349: 1 (11) 500 555-0137 | G349: Viktoria-Luise-Platz 43 | J349: United States | N349: 59251979
A350: 11348 | C350: 2024-01-02T14:16:06.9086921Z | D350: Shawn Rai | E350: shawn19@gmail.com | F350: 1 (11) 500 555-0117 | G350: Westheimer Straße 7606 | J350: United States | N350: 59251980
A351: 11349 | C351: 2024-01-02T14:16:06.9086921Z | D351: Mindy Luo | E351: mindy10@gmail.com | F351: 1 (11) 500 555-0194 | G351: Brunnenstr 7566 | J351: United States | N351: 59251981
A352: 11350 | C352: 2024-01-02T14:16:06.9086921Z | D352: Cara Zhou | E352: cara5@gmail.com | F352: 1 (11) 500 555-0118 | G352: 7280 Greendell Pl | J352: United States | N352: 59251982
A353: 11351 | C353: 2024-01-02T14:16:06.9086921Z | D353: Anne Ramos | E353: anne19@gmail.com | F353: 1 (11) 500 555-0148 | G353: 7113 Eastgate Ave. | J353: United States | N353: 59251983
A354: 11352 | C354: 2024-01-02T14:16:06.9086921Z | D354: Raymond Rodriguez | E354: raymond20@gmail.com | F354: 1 (11) 500 555-0131 | G354: 24 | H354: impasse Ste-Madeleine | J354: United States | N354: 59251984
A355: 11353 | C355: 2024-01-02T14:16:06.9086921Z | D355: Carrie Ortega | E355: carrie19@gmail.com | F355: 1 (11) 500 555-0111 | G355: 1883 Cowell Rd. | J355: United States | N355: 59251985
A356: 11354 | C356: 2024-01-02T14:16:06.9086921Z | D356: Deanna Suarez | E356: deanna45@gmail.com | F356: 1 (11) 500 555-0146 | G356: Dunckerstr 22525 | J356: United States | N356: 59251986
A357: 11355 | C357: 2024-01-02T14:16:06.9086921Z | D357: Roberto Gutierrez | E357: roberto11@gmail.com | F357: 1 (11) 500 555-0124 | G357: 3545 Chickpea Ct. | J357: United States | N357: 59251987
A358: 11356 | C358: 2024-01-02T14:16:06.9086921Z | D358: Terrence Carson | E358: terrence15@gmail.com | F358: 1 (11) 500 555-0189 | G358: 6613 Thornhill Place | J358: United States | N358: 59251988
A359: 11357 | C359: 2024-01-02T14:16:06.9086921Z | D359: Ramon Ye | E359: ramon9@gmail.com | F359: 1 (11) 500 555-0143 | G359: 3245 Vista Oak Dr. | J359: United States | N359: 59251989
A360: 11358 | C360: 2024-01-02T14:16:06.9086921Z | D360: Cynthia Malhotra | E360: cynthia9@gmail.com | F360: 1 (11) 500 555-0187 | G360: 6757 Pamplona Ct. | J360: United States | N360: 59251990
A361: 11359 | C361: 2024-01-02T14:16:06.9086921Z | D361: Jarrod Prasad | E361: jarrod9@gmail.com | F361: 1 (11) 500 555-0154 | G361: 7657 H St. | J361: United States | N361: 59251991
A362: 11360 | C362: 2024-01-02T14:16:06.9086921Z | D362: Tyrone Serrano | E362: tyrone15@gmail.com | F362: 1 (11) 500 555-0176 | G362: 3767 View Dr. | J362: United States | N362: 59251992
A363: 11361 | C363: 2024-01-02T14:16:06.9086921Z | D363: Cindy Ramos | E363: cindy22@gmail.com | F363: 1 (11) 500 555-0173 | G363: 6565 Jamie Way | J363: United States | N363: 59251993
A364: 11362 | C364: 2024-01-02T14:16:06.9086921Z | D364: Damien Shan | E364: damien26@gmail.com | F364: 1 (11) 500 555-0142 | G364: 5312 Riverwood Circle | J364: United States | N364: 59251994
A365: 11363 | C365: 2024-01-02T14:16:06.9086921Z | D365: Julian Ross | E365: julian5@gmail.com | F365: 1 (11) 500 555-0126 | G365: 3346 Larkwood Ct. | J365: United States | N365: 59251995
A366: 11364 | C366: 2024-01-02T14:16:06.9086921Z | D366: Jennifer Collins | E366: jennifer6@gmail.com | F366: 1 (11) 500 555-0196 | G366: 4536 Killdeer Court | J366: United States | N366: 59251996
... A380: 11378 | C380: 2024-01-02T14:16:06.9086921Z | D380: Shannon Liang | E380: shannon15@gmail.com | F380: 1 (11) 500 555-0159 | G380: 7445 Meaham Drive | J380: United States | N380: 59252010
A381: 11379 | C381: 2024-01-02T14:16:06.9086921Z | D381: Gary Vazquez | E381: gary25@gmail.com | F381: 1 (11) 500 555-0130 | G381: 5 | H381: rue de la Cavalerie | J381: United States | N381: 59252011
A382: 11380 | C382: 2024-01-02T14:16:06.9086921Z | D382: Mitchell Kumar | E382: mitchell7@gmail.com | F382: 1 (11) 500 555-0119 | G382: Husemann Straße 6464 | J382: United States | N382: 59252012
A383: 11381 | C383: 2024-01-02T14:16:06.9086921Z | D383: Meredith Raman | E383: meredith11@gmail.com | F383: 1 (11) 500 555-0162 | G383: 6092 Chestnut | J383: United States | N383: 59252013
A384: 11382 | C384: 2024-01-02T14:16:06.9086921Z | D384: Edward Patterson | E384: edward59@gmail.com | F384: 1 (11) 500 555-0118 | G384: 211 | H384: avenue Foch | J384: United States | N384: 59252014
A385: 11383 | C385: 2024-01-02T14:16:06.9086921Z | D385: Marie Gill | E385: marie37@gmail.com | F385: 1 (11) 500 555-0192 | G385: 571 | H385: rue Malar | J385: United States | N385: 59252015
A386: 11384 | C386: 2024-01-02T14:16:06.9086921Z | D386: Tiffany Wang | E386: tiffany1@gmail.com | F386: 1 (11) 500 555-0192 | G386: 5 | H386: rue Malar | J386: United States | N386: 59252016
A387: 11385 | C387: 2024-01-02T14:16:06.9086921Z | D387: Miguel Allen | E387: miguel24@gmail.com | F387: 1 (11) 500 555-0128 | G387: 6834 Violetta | J387: United States | N387: 59252017
A388: 11386 | C388: 2024-01-02T14:16:06.9086921Z | D388: Jaclyn Cai | E388: jaclyn22@gmail.com | F388: 1 (11) 500 555-0164 | G388: Postfach 55 00 00 | J388: United States | N388: 59252018
A389: 11387 | C389: 2024-01-02T14:16:06.9086921Z | D389: Megan Ramirez | E389: megan44@gmail.com | F389: 1 (11) 500 555-0192 | G389: 507 Sahara Drive | J389: United States | N389: 59252019
A390: 11388 | C390: 2024-01-02T14:16:06.9086921Z | D390: Joseph Martin | E390: joseph21@gmail.com | F390: 1 (11) 500 555-0143 | G390: 7028 San Gabriel Dr. | J390: United States | N390: 59252020
A391: 11389 | C391: 2024-01-02T14:16:06.9086921Z | D391: Karl Shan | E391: karl11@gmail.com | F391: 1 (11) 500 555-0198 | G391: Nollendorfplatz 48 | J391: United States | N391: 59252021
A392: 11390 | C392: 2024-01-02T14:16:06.9086921Z | D392: Christine Raji | E392: christine16@gmail.com | F392: 1 (11) 500 555-0153 | G392: 11 | H392: boulevard Tremblay | J392: United States | N392: 59252022
A393: 11391 | C393: 2024-01-02T14:16:06.9086921Z | D393: Lindsay Xie | E393: lindsay3@gmail.com | F393: 1 (11) 500 555-0115 | G393: Am Grossen Dern 4624 | J393: United States | N393: 59252023
A394: 11392 | C394: 2024-01-02T14:16:06.9086921Z | D394: Willie Zhao | E394: willie8@gmail.com | F394: 1 (11) 500 555-0120 | G394: Königstr 282 | J394: United States | N394: 59252024
A395: 11393 | C395: 2024-01-02T14:16:06.9086921Z | D395: Kurt Pal | E395: kurt12@gmail.com | F395: 1 (11) 500 555-0117 | G395: 55 | H395: avenue de l´ Union Centrale | J395: United States | N395: 59252025
A396: 11394 | C396: 2024-01-02T14:16:06.9086921Z | D396: George McDonald | E396: george13@gmail.com | F396: 1 (11) 500 555-0150 | G396: 9186 West Boyd Rd. | J396: United States | N396: 59252026
A397: 11395 | C397: 2024-01-02T14:16:06.9086921Z | D397: Beth Gutierrez | E397: beth13@gmail.com | F397: 1 (11) 500 555-0110 | G397: Rehstr 1346 | J397: United States | N397: 59252027
A398: 11396 | C398: 2024-01-02T14:16:06.9086921Z | D398: Ian Lopez | E398: ian27@gmail.com | F398: 1 (11) 500 555-0182 | G398: Zur Lindung 6 | J398: United States | N398: 59252028
A399: 11397 | C399: 2024-01-02T14:16:06.9086921Z | D399: Latoya Shan | E399: latoya9@gmail.com | F399: 1 (11) 500 555-0122 | G399: Attaché de Presse | J399: United States | N399: 59252029
A400: 11398 | C400: 2024-01-02T14:16:06.9086921Z | D400: Colin Nath | E400: colin41@gmail.com | F400: 1 (11) 500 555-0115 | G400: 8900 Escobar | J400: United States | N400: 59252030
A401: 11399 | C401: 2024-01-02T14:16:06.9086921Z | D401: Brenda Mehta | E401: brenda17@gmail.com | F401: 1 (11) 500 555-0155 | G401: 11 | H401: avenue du Port | J401: United States | N401: 59252031
A402: 11400 | C402: 2024-01-02T14:16:06.9086921Z | D402: Franklin Raji | E402: franklin38@gmail.com | F402: 1 (11) 500 555-0180 | G402: 3477 Mt. Washington Way | J402: United States | N402: 59252032
A403: 11401 | C403: 2024-01-02T14:16:06.9086921Z | D403: Linda Navarro | E403: linda25@gmail.com | F403: 1 (11) 500 555-0189 | G403: 6 | H403: route de Marseille | J403: United States | N403: 59252033
A404: 11402 | C404: 2024-01-02T14:16:06.9086921Z | D404: Kelli Cai | E404: kelli21@gmail.com | F404: 1 (11) 500 555-0145 | G404: 1216 | H404: place de la Concorde | J404: United States | N404: 59252034
A405: 11403 | C405: 2024-01-02T14:16:06.9086921Z | D405: Nancy Schmidt | E405: nancy13@gmail.com | F405: 1 (11) 500 555-0150 | G405: 340 | H405: boulevard d´Albi | J405: United States | N405: 59252035
A406: 11404 | C406: 2024-01-02T14:16:06.9086921Z | D406: Megan Taylor | E406: megan12@gmail.com | F406: 1 (11) 500 555-0178 | G406: Berliner Platz 43 | J406: United States | N406: 59252036
A407: 11405 | C407: 2024-01-02T14:16:06.9086921Z | D407: Bonnie Goel | E407: bonnie25@gmail.com | F407: 1 (11) 500 555-0143 | G407: Carlsplatz 89 | J407: United States | N407: 59252037
A408: 11406 | C408: 2024-01-02T14:16:06.9086921Z | D408: Latoya Xu | E408: latoya4@gmail.com | F408: 1 (11) 500 555-0141 | G408: 101 | H408: rue de Terre Neuve | J408: United States | N408: 59252038
A409: 11407 | C409: 2024-01-02T14:16:06.9086921Z | D409: Mario She | E409: mario0@gmail.com | F409: 1 (11) 500 555-0156 | G409: Conesweg 720 | J409: United States | N409: 59252039
A410: 11408 | C410: 2024-01-02T14:16:06.9086921Z | D410: Darren Gill | E410: darren36@gmail.com | F410: 1 (11) 500 555-0166 | G410: 8132 Twincreek Ct | J410: United States | N410: 59252040
A411: 11409 | C411: 2024-01-02T14:16:06.9086921Z | D411: Jacqueline Hayes | E411: jacqueline23@gmail.com | F411: 1 (11) 500 555-0162 | G411: 33 | H411: rue Georges-Clémenceau | J411: United States | N411: 59252041
A412: 11410 | C412: 2024-01-02T14:16:06.9086921Z | D412: Maurice Goel | E412: maurice20@gmail.com | F412: 1 (11) 500 555-0179 | G412: 15 | H412: avenue de la Gare | J412: United States | N412: 59252042
A413: 11411 | C413: 2024-01-02T14:16:06.9086921Z | D413: Devin Ross | E413: devin69@gmail.com | F413: 1 (11) 500 555-0172 | G413: Postenweg 2428 | J413: United States | N413: 59252043
A414: 11412 | C414: 2024-01-02T14:16:06.9086921Z | D414: Sydney Bryant | E414: sydney40@gmail.com | F414: 1 (11) 500 555-0156 | G414: Postfach 99 92 92 | J414: United States | N414: 59252044
A415: 11413 | C415: 2024-01-02T14:16:06.9086921Z | D415: Megan Stewart | E415: megan27@gmail.com | F415: 1 (11) 500 555-0116 | G415: 8192 Seagull Court | J415: United States | N415: 59252045
...

Sheet dimcusttable
A2: Tables | B2: CustInfo
A5: ColumnsNeeded | B5: If name is blank, retain the original column name
A7: Table | B7: Column | C7: Logic | D7: Name
A8: CustInfo | B8: CustomerId
A9: CustInfo | B9: LastProcessedChange_DateTime
A10: CustInfo | B10: DataLakeModified_DateTime | C10: ConvertToCST
A11: CustInfo | B11: CustomerName
A12: CustInfo | B12: Email
A13: CustInfo | B13: Phone
A14: CustInfo | B14: Address
A15: CustInfo | B15: City
A16: CustInfo | B16: State
A17: CustInfo | B17: Country
A18: CustInfo | B18: ZipCode
A19: CustInfo | B19: Region
A20: CustInfo | B20: SignupDate
A21: CustInfo | B21: RecordId | D21: CustRecordId

Sheet PromoTable
A1: PromotionId | B1: LastProcessedChange_DateTime | C1: DataLakeModified_DateTime | D1: PromotionName | E1: PromoCode | F1: PromoType | G1: PromoPercentage | H1: ValidFrom | I1: ValidTo | J1: IsActive | K1: RecordId
A2: 1 | C2: 2024-01-02T14:16:06.9086921Z | D2: New Year offer | E2: NYO22 | F2: Percentage | G2: 0.02 | H2: 2022-01-01T00:00:00.0000000Z | I2: 2022-01-31T00:00:00.0000000Z | J2: 0 | K2: 56218723
A3: 2 | C3: 2024-01-02T14:16:06.9086921Z | D3: New Year offer | E3: NYO23 | F3: Percentage | G3: 0.02 | H3: 2023-01-01T00:00:00.0000000Z | I3: 2023-01-31T00:00:00.0000000Z | J3: 0 | K3: 56218724
A4: 3 | C4: 2024-01-02T14:16:06.9086921Z | D4: New Year offer | E4: NYO24 | F4: Percentage | G4: 0.02 | H4: 2024-01-01T00:00:00.0000000Z | I4: 2024-01-31T00:00:00.0000000Z | J4: 0 | K4: 56218725
A5: 4 | C5: 2024-01-02T14:16:06.9086921Z | D5: New Year offer | E5: NYO25 | F5: Percentage | G5: 0.02 | H5: 2025-01-01T00:00:00.0000000Z | I5: 2025-01-31T00:00:00.0000000Z | J5: 1 | K5: 56218726
A6: 5 | C6: 2024-01-02T14:16:06.9086921Z | D6: Volume Discount 11 to 20 | E6: VD11 | F6: Volume | G6: 0.005 | J6: 1 | K6: 56218727
A7: 6 | C7: 2024-01-02T14:16:06.9086921Z | D7: Volume Discount 21 to 40 | E7: VD21 | F7: Volume | G7: 0.01 | J7: 1 | K7: 56218728
A8: 7 | C8: 2024-01-02T14:16:06.9086921Z | D8: Volume Discount 41 to 60 | E8: VD41 | F8: Volume | G8: 0.015 | J8: 1 | K8: 56218729
A9: 8 | C9: 2024-01-02T14:16:06.9086921Z | D9: Volume Discount > 60 | E9: VD61 | F9: Volume | G9: 0.02 | J9: 1 | K9: 56218730

Sheet dimpromotable
A1: Tables | B1: Promotable
A4: ColumnsNeeded | B4: If name is blank, retain the original column name
A6: Table | B6: Column | C6: Logic | D6: Name
A7: Promotable | B7: PromotionId
A8: Promotable | B8: LastProcessedChange_DateTime
A9: Promotable | B9: DataLakeModified_DateTime | C9: ConvertToCST
A10: Promotable | B10: PromotionName
A11: Promotable | B11: PromoCode
A12: Promotable | B12: PromoType
A13: Promotable | B13: PromoPercentage
A14: Promotable | B14: ValidFrom
A15: Promotable | B15: ValidTo
A16: Promotable | B16: IsActive
A17: Promotable | B17: RecordId | D17: PromoRecordId

Sheet PaymentTypes
A1: PaymentTypeId | B1: LastProcessedChange_DateTime | C1: DataLakeModified_DateTime | D1: PaymentTypeName | E1: RecordId
A2: 1 | C2: 2024-01-02T14:16:06.9086921Z | D2: CashOnDelivery | E2: 23581297
A3: 2 | C3: 2024-01-02T14:16:06.9086921Z | D3: CreditCard | E3: 23581298
A4: 3 | C4: 2024-01-02T14:16:06.9086921Z | D4: DebitCard | E4: 23581299

Sheet HR

Sheet WorkerTable
A1: WorkerID | B1: LastProcessedChange_DateTime | C1: DataLakeModified_DateTime | D1: SupervisorId | E1: WorkerName | F1: WorkerEmail | G1: Phone | H1: DOJ | I1: DOL | J1: Vertical | K1: Type | L1: PayPerAnnum | M1: Rate | N1: RecordId
A2: 1 | C2: 2024-01-02T14:16:06.9086921Z | D2: 18 | E2: Guy Gilbert | F2: guy1@oaon.com | G2: 320-555-0195 | H2: 43858 | J2: Marketing | K2: Contract | L2: 950884 | N2: 39184501
A3: 2 | C3: 2024-01-02T14:16:06.9086921Z | D3: 7 | E3: Kevin Brown | F3: kevin0@oaon.com | G3: 150-555-0189 | H3: 44069 | J3: Purchase | K3: Contract | L3: 298253 | N3: 39184502
A4: 3 | C4: 2024-01-02T14:16:06.9086921Z | D4: 14 | E4: Roberto Tamburello | F4: roberto0@oaon.com | G4: 212-555-0187 | H4: 44358 | J4: QualityControl | K4: FullTime | L4: 977624 | N4: 39184503
A5: 4 | C5: 2024-01-02T14:16:06.9086921Z | D5: 3 | E5: Rob Walters | F5: rob0@oaon.com | G5: 612-555-0100 | H5: 44382 | I5: 44778 | J5: HR | K5: FullTime | L5: 116722 | N5: 39184504
A6: 5 | C6: 2024-01-02T14:16:06.9086921Z | D6: 3 | E6: Rob Walters | F6: rob0@oaon.com | G6: 612-555-0100 | H6: 45288 | J6: Sales | K6: Contract | L6: 920802 | N6: 39184505
A7: 6 | C7: 2024-01-02T14:16:06.9086921Z | D7: 267 | E7: Thierry D'Hers | F7: thierry0@oaon.com | G7: 168-555-0183 | H7: 44388 | J7: Marketing | K7: Contract | L7: 846918 | N7: 39184506
A8: 7 | C8: 2024-01-02T14:16:06.9086921Z | D8: 112 | E8: David Bradley | F8: david0@oaon.com | G8: 913-555-0172 | H8: 44397 | I8: 45402 | J8: Logistics | K8: FullTime | L8: 41642 | N8: 39184507
A9: 8 | C9: 2024-01-02T14:16:06.9086921Z | D9: 112 | E9: David Bradley | F9: david0@oaon.com | G9: 913-555-0172 | H9: 44969 | J9: HR | K9: FullTime | L9: 356119 | N9: 39184508
A10: 9 | C10: 2024-01-02T14:16:06.9086921Z | D10: 23 | E10: JoLynn Dobney | F10: jolynn0@oaon.com | G10: 903-555-0145 | H10: 44403 | J10: Admin | K10: FullTime | L10: 498392 | N10: 39184509
A11: 10 | C11: 2024-01-02T14:16:06.9086921Z | D11: 189 | E11: Ruth Ellerbrock | F11: ruth0@oaon.com | G11: 145-555-0130 | H11: 44414 | J11: Marketing | K11: FullTime | L11: 540306 | N11: 39184510
A12: 11 | C12: 2024-01-02T14:16:06.9086921Z | D12: 3 | E12: Gail Erickson | F12: gail0@oaon.com | G12: 849-555-0139 | H12: 44414 | J12: HR | K12: Contract | L12: 425151 | N12: 39184511
A13: 12 | C13: 2024-01-02T14:16:06.9086921Z | D13: 189 | E13: Barry Johnson | F13: barry0@oaon.com | G13: 206-555-0180 | H13: 44415 | J13: Purchase | K13: Contract | L13: 992399 | N13: 39184512
A14: 13 | C14: 2024-01-02T14:16:06.9086921Z | D14: 3 | E14: Jossef Goldberg | F14: jossef0@oaon.com | G14: 122-555-0189 | H14: 44432 | J14: Purchase | K14: FullTime | L14: 781055 | N14: 39184513
A15: 14 | C15: 2024-01-02T14:16:06.9086921Z | D15: 112 | E15: Terri Duffy | F15: terri0@oaon.com | G15: 819-555-0175 | H15: 44439 | J15: Sales | K15: FullTime | L15: 48455 | N15: 39184514
A16: 15 | C16: 2024-01-02T14:16:06.9086921Z | D16: 189 | E16: Sidney Higa | F16: sidney0@oaon.com | G16: 424-555-0189 | H16: 44441 | J16: Marketing | K16: Contract | L16: 105486 | N16: 39184515
A17: 16 | C17: 2024-01-02T14:16:06.9086921Z | D17: 23 | E17: Taylor Maxwell | F17: taylor0@oaon.com | G17: 508-555-0165 | H17: 44447 | J17: Sales | K17: Contract | L17: 503859 | N17: 39184516
A18: 17 | C18: 2024-01-02T14:16:06.9086921Z | D18: 189 | E18: Jeffrey Ford | F18: jeffrey0@oaon.com | G18: 984-555-0185 | H18: 44459 | J18: Admin | K18: Contract | L18: 171564 | N18: 39184517
A19: 18 | C19: 2024-01-02T14:16:06.9086921Z | D19: 23 | E19: Jo Brown | F19: jo0@oaon.com | G19: 632-555-0129 | H19: 44466 | J19: Sales | K19: Contract | L19: 650735 | N19: 39184518
A20: 19 | C20: 2024-01-02T14:16:06.9086921Z | D20: 189 | E20: Doris Hartwig | F20: doris0@oaon.com | G20: 328-555-0150 | H20: 44478 | J20: Admin | K20: Contract | L20: 423496 | N20: 39184519
... A98: 97 | C98: 2024-01-02T14:16:06.9086921Z | D98: 76 | E98: Nuan Yu | F98: nuan0@oaon.com | G98: 913-555-0184 | H98: 44779 | J98: Purchase | K98: Contract | L98: 813515 | N98: 39184597
A99: 98 | C99: 2024-01-02T14:16:06.9086921Z | D99: 46 | E99: William Vong | F99: william0@oaon.com | G99: 148-555-0145 | H99: 44780 | I99: 45572 | J99: Logistics | K99: Contract | L99: 553015 | N99: 39184598
A100: 99 | C100: 2024-01-02T14:16:06.9086921Z | D100: 46 | E100: William Vong | F100: william0@oaon.com | G100: 148-555-0145 | H100: 45748 | J100: Logistics | K100: Contract | L100: 76319 | N100: 39184599
A101: 100 | C101: 2024-01-02T14:16:06.9086921Z | D101: 177 | E101: Bjorn Rettig | F101: bjorn0@oaon.com | G101: 199-555-0117 | H101: 44780 | J101: Admin | K101: Contract | L101: 203220 | N101: 39184600
A102: 101 | C102: 2024-01-02T14:16:06.9086921Z | D102: 201 | E102: Scott Gode | F102: scott0@oaon.com | G102: 391-555-0138 | H102: 44781 | J102: HR | K102: FullTime | L102: 473339 | N102: 39184601
A103: 102 | C103: 2024-01-02T14:16:06.9086921Z | D103: 89 | E103: Michael Rothkugel | F103: michael1@oaon.com | G103: 454-555-0119 | H103: 44783 | J103: Logistics | K103: Contract | L103: 260029 | N103: 39184602
A104: 103 | C104: 2024-01-02T14:16:06.9086921Z | D104: 147 | E104: Lane Sacksteder | F104: lane0@oaon.com | G104: 200-555-0117 | H104: 44784 | J104: Sales | K104: FullTime | L104: 395830 | N104: 39184603
A105: 104 | C105: 2024-01-02T14:16:06.9086921Z | D105: 16 | E105: Pete Male | F105: pete0@oaon.com | G105: 768-555-0123 | H105: 44784 | J105: Purchase | K105: FullTime | L105: 356746 | N105: 39184604
A106: 105 | C106: 2024-01-02T14:16:06.9086921Z | D106: 44 | E106: Dan Bacon | F106: dan0@oaon.com | G106: 166-555-0159 | H106: 44784 | J106: Sales | K106: FullTime | L106: 943886 | N106: 39184605
A107: 106 | C107: 2024-01-02T14:16:06.9086921Z | D107: 143 | E107: David Barber | F107: david5@oaon.com | G107: 477-555-0132 | H107: 44785 | J107: HR | K107: FullTime | L107: 778747 | N107: 39184606
A108: 107 | C108: 2024-01-02T14:16:06.9086921Z | D108: 76 | E108: Lolan Song | F108: lolan0@oaon.com | G108: 582-555-0178 | H108: 44785 | J108: Admin | K108: FullTime | L108: 950052 | N108: 39184607
A109: 108 | C109: 2024-01-02T14:16:06.9086921Z | D109: 214 | E109: Paula Nartker | F109: paula1@oaon.com | G109: 476-555-0119 | H109: 44785 | J109: Sales | K109: FullTime | L109: 355202 | N109: 39184608
A110: 109 | C110: 2024-01-02T14:16:06.9086921Z | D110: 7 | E110: Mary Gibson | F110: mary0@oaon.com | G110: 531-555-0183 | H110: 44785 | J110: Admin | K110: FullTime | L110: 627782 | N110: 39184609
A111: 110 | C111: 2024-01-02T14:16:06.9086921Z | D111: 40 | E111: Mindaugas Krapauskas | F111: mindaugas0@oaon.com | G111: 637-555-0120 | H111: 44786 | J111: HR | K111: FullTime | L111: 318651 | N111: 39184610
A112: 111 | C112: 2024-01-02T14:16:06.9086921Z | D112: 23 | E112: Eric Gubbels | F112: eric0@oaon.com | G112: 260-555-0119 | H112: 44787 | J112: Admin | K112: FullTime | L112: 638256 | N112: 39184611
A113: 112 | C113: 2024-01-02T14:16:06.9086921Z | D113: NULL | E113: Ken Sánchez | F113: ken0@oaon.com | G113: 697-555-0142 | H113: 44787 | J113: Logistics | K113: Contract | L113: 736751 | N113: 39184612
A114: 113 | C114: 2024-01-02T14:16:06.9086921Z | D114: 138 | E114: Jason Watters | F114: jason0@oaon.com | G114: 571-555-0179 | H114: 44787 | J114: HR | K114: Contract | L114: 601729 | N114: 39184613
A115: 114 | C115: 2024-01-02T14:16:06.9086921Z | D115: 43 | E115: Mark Harrington | F115: mark0@oaon.com | G115: 147-555-0179 | H115: 44788 | J115: Logistics | K115: Contract | L115: 101519 | N115: 39184614
A116: 115 | C116: 2024-01-02T14:16:06.9086921Z | D116: 163 | E116: Janeth Esteves | F116: janeth0@oaon.com | G116: 540-555-0191 | H116: 44788 | J116: Marketing | K116: Contract | L116: 676860 | N116: 39184615
A117: 116 | C117: 2024-01-02T14:16:06.9086921Z | D117: 188 | E117: Marc Ingle | F117: marc0@oaon.com | G117: 234-555-0169 | H117: 44789 | J117: QualityControl | K117: Contract | L117: 720330 | N117: 39184616
A118: 117 | C118: 2024-01-02T14:16:06.9086921Z | D118: 162 | E118: Gigi Matthew | F118: gigi0@oaon.com | G118: 185-555-0186 | H118: 44789 | J118: Logistics | K118: Contract | L118: 719412 | N118: 39184617
A119: 118 | C119: 2024-01-02T14:16:06.9086921Z | D119: 111 | E119: Paul Singh | F119: paul1@oaon.com | G119: 727-555-0112 | H119: 44790 | J119: QualityControl | K119: Contract | L119: 387183 | N119: 39184618
A120: 119 | C120: 2024-01-02T14:16:06.9086921Z | D120: 214 | E120: Frank Lee | F120: frank0@oaon.com | G120: 158-555-0191 | H120: 44790 | J120: QualityControl | K120: FullTime | L120: 738195 | N120: 39184619
A121: 120 | C121: 2024-01-02T14:16:06.9086921Z | D121: 44 | E121: François Ajenstat | F121: françois0@oaon.com | G121: 785-555-0110 | H121: 44790 | J121: Marketing | K121: Contract | L121: 84253 | N121: 39184620
A122: 121 | C122: 2024-01-02T14:16:06.9086921Z | D122: 16 | E122: Diane Tibbott | F122: diane2@oaon.com | G122: 361-555-0180 | H122: 44791 | J122: Marketing | K122: FullTime | L122: 696930 | N122: 39184621
A123: 122 | C123: 2024-01-02T14:16:06.9086921Z | D123: 7 | E123: Jill Williams | F123: jill0@oaon.com | G123: 510-555-0121 | H123: 44791 | J123: Logistics | K123: FullTime | L123: 597745 | N123: 39184622
A124: 123 | C124: 2024-01-02T14:16:06.9086921Z | D124: 40 | E124: Angela Barbariol | F124: angela0@oaon.com | G124: 150-555-0194 | H124: 44793 | J124: Marketing | K124: FullTime | L124: 485721 | N124: 39184623
A125: 124 | C125: 2024-01-02T14:16:06.9086921Z | D125: 87 | E125: Matthias Berndt | F125: matthias0@oaon.com | G125: 139-555-0120 | H125: 44793 | J125: Purchase | K125: FullTime | L125: 651551 | N125: 39184624
... A143: 142 | C143: 2024-01-02T14:16:06.9086921Z | D143: 143 | E143: David Liu | F143: david6@oaon.com | G143: 646-555-0185 | H143: 44803 | J143: Marketing | K143: FullTime | L143: 816543 | N143: 39184642
A144: 143 | C144: 2024-01-02T14:16:06.9086921Z | D144: 112 | E144: Laura Norman | F144: laura1@oaon.com | G144: 615-555-0110 | H144: 44804 | I144: 44985 | J144: HR | K144: Contract | L144: 824400 | N144: 39184643
A145: 144 | C145: 2024-01-02T14:16:06.9086921Z | D145: 112 | E145: Laura Norman | F145: laura1@oaon.com | G145: 615-555-0110 | H145: 46551 | J145: Sales | K145: FullTime | L145: 166238 | N145: 39184644
A146: 145 | C146: 2024-01-02T14:16:06.9086921Z | D146: 40 | E146: Michael Patten | F146: michael2@oaon.com | G146: 441-555-0195 | H146: 44804 | J146: Logistics | K146: Contract | L146: 872829 | N146: 39184645
A147: 146 | C147: 2024-01-02T14:16:06.9086921Z | D147: 138 | E147: Andy Ruth | F147: andy0@oaon.com | G147: 118-555-0110 | H147: 44804 | J147: QualityControl | K147: FullTime | L147: 924810 | N147: 39184646
A148: 147 | C148: 2024-01-02T14:16:06.9086921Z | D148: 23 | E148: Yuhong Li | F148: yuhong0@oaon.com | G148: 965-555-0155 | H148: 44805 | J148: Purchase | K148: Contract | L148: 307798 | N148: 39184647
A149: 148 | C149: 2024-01-02T14:16:06.9086921Z | D149: 163 | E149: Robert Rounthwaite | F149: robert0@oaon.com | G149: 589-555-0147 | H149: 44806 | J149: Logistics | K149: FullTime | L149: 877157 | N149: 39184648
A150: 149 | C150: 2024-01-02T14:16:06.9086921Z | D150: 43 | E150: Andreas Berglund | F150: andreas0@oaon.com | G150: 181-555-0124 | H150: 44806 | J150: Sales | K150: Contract | L150: 963843 | N150: 39184649
A151: 150 | C151: 2024-01-02T14:16:06.9086921Z | D151: 188 | E151: Reed Koch | F151: reed0@oaon.com | G151: 678-555-0110 | H151: 44806 | J151: Sales | K151: FullTime | L151: 126478 | N151: 39184650
A152: 151 | C152: 2024-01-02T14:16:06.9086921Z | D152: 147 | E152: Linda Randall | F152: linda1@oaon.com | G152: 696-555-0157 | H152: 44807 | J152: Logistics | K152: Contract | L152: 918790 | N152: 39184651
A153: 152 | C153: 2024-01-02T14:16:06.9086921Z | D153: 112 | E153: James Hamilton | F153: james1@oaon.com | G153: 870-555-0122 | H153: 44807 | J153: Sales | K153: Contract | L153: 245510 | N153: 39184652
A154: 153 | C154: 2024-01-02T14:16:06.9086921Z | D154: 44 | E154: Ramesh Meyyappan | F154: ramesh0@oaon.com | G154: 182-555-0134 | H154: 44807 | J154: Admin | K154: FullTime | L154: 697393 | N154: 39184653
A155: 154 | C155: 2024-01-02T14:16:06.9086921Z | D155: 44 | E155: Stephanie Conroy | F155: stephanie0@oaon.com | G155: 594-555-0110 | H155: 44808 | J155: Logistics | K155: FullTime | L155: 761197 | N155: 39184654
A156: 155 | C156: 2024-01-02T14:16:06.9086921Z | D156: 111 | E156: Samantha Smith | F156: samantha0@oaon.com | G156: 587-555-0114 | H156: 44808 | J156: QualityControl | K156: Contract | L156: 228039 | N156: 39184655
... A278: 277 | C278: 2024-01-02T14:16:06.9086921Z | D278: 112 | E278: Brian Welcker | F278: brian3@oaon.com | G278: 716-555-0127 | H278: 45550 | J278: Marketing | K278: FullTime | L278: 858470 | N278: 39184777
A279: 278 | C279: 2024-01-02T14:16:06.9086921Z | D279: 73 | E279: Sheela Word | F279: sheela0@oaon.com | G279: 210-555-0193 | H279: 45560 | I279: 45682 | J279: QualityControl | K279: Contract | L279: 804913 | N279: 39184778
A280: 281 | C280: 2024-01-02T14:16:06.9086921Z | D280: 272 | E280: Michael Blythe | F280: michael9@oaon.com | G280: 257-555-0154 | H280: 45655 | J280: Admin | K280: Contract | L280: 743879 | N280: 39184781
A281: 282 | C281: 2024-01-02T14:16:06.9086921Z | D281: 272 | E281: Linda Mitchell | F281: linda3@oaon.com | G281: 883-555-0116 | H281: 45655 | J281: Logistics | K281: Contract | L281: 352809 | N281: 39184782
A282: 283 | C282: 2024-01-02T14:16:06.9086921Z | D282: 272 | E282: Jillian Carson | F282: jillian0@oaon.com | G282: 517-555-0117 | H282: 45655 | J282: Admin | K282: Contract | L282: 734375 | N282: 39184783
A283: 284 | C283: 2024-01-02T14:16:06.9086921Z | D283: 272 | E283: Garrett Vargas | F283: garrett1@oaon.com | G283: 922-555-0165 | H283: 45655 | J283: HR | K283: Contract | L283: 467673 | N283: 39184784
A284: 285 | C284: 2024-01-02T14:16:06.9086921Z | D284: 272 | E284: Tsvi Reiter | F284: tsvi0@oaon.com | G284: 664-555-0112 | H284: 45655 | J284: Logistics | K284: FullTime | L284: 434383 | N284: 39184785
A285: 286 | C285: 2024-01-02T14:16:06.9086921Z | D285: 272 | E285: Pamela Ansman-Wolfe | F285: pamela0@oaon.com | G285: 340-555-0193 | H285: 45655 | J285: Purchase | K285: Contract | L285: 548083 | N285: 39184786
A286: 287 | C286: 2024-01-02T14:16:06.9086921Z | D286: 272 | E286: Shu Ito | F286: shu0@oaon.com | G286: 330-555-0120 | H286: 45655 | J286: Marketing | K286: FullTime | L286: 877730 | N286: 39184787
A287: 288 | C287: 2024-01-02T14:16:06.9086921Z | D287: 272 | E287: José Saraiva | F287: josé1@oaon.com | G287: 185-555-0169 | H287: 45655 | J287: Purchase | K287: FullTime | L287: 861820 | N287: 39184788
A288: 289 | C288: 2024-01-02T14:16:06.9086921Z | D288: 272 | E288: David Campbell | F288: david8@oaon.com | G288: 740-555-0182 | H288: 45655 | J288: Marketing | K288: Contract | L288: 248996 | N288: 39184789

Sheet dimvertical
A1: Tables | B1: WorkerTable
A4: ColumnsNeeded | B4: If name is blank, retain the original column name
A6: Table | B6: Column | C6: Logic | D6: Name | E6: Comments
B7: VerticalId | E7: Generate incremental and sequential ids starting from 1 for each row
A8: WorkerTable | B8: Vertical

Sheet dimworkertable
A1: Table | B1: Joinkey | C1: Table | D1: Joinkey
A2: WorkerTable | B2: Vertical | C2: dimvertical | D2: Vertical
A8: ColumnsNeeded | B8: If name is blank, retain the original column name
A10: Table | B10: Column | C10: Logic | D10: Name | E10: Comments
A11: WorkerTable | B11: WorkerID
A12: WorkerTable | B12: LastProcessedChange_DateTime
A13: WorkerTable | B13: DataLakeModified_DateTime | C13: ConvertToCST
A14: WorkerTable | B14: SupervisorId
A15: WorkerTable | B15: WorkerName
A16: WorkerTable | B16: WorkerEmail
A17: WorkerTable | B17: Phone
A18: WorkerTable | B18: DOJ
A19: WorkerTable | B19: DOL
A20: dimvertical | B20: VerticalId
A21: WorkerTable | B21: Type
A22: WorkerTable | B22: PayPerAnnum
A23: WorkerTable | B23: Rate
A24: WorkerTable | B24: RecordId | D24: WorkerRecordId

Sheet DQ

Sheet DQRuleType
A1: DQRuleId | B1: DQRuleName

Sheet DQRuleMetaData

Sheet DQRuleResults

Sheet Misc

Sheet Currency
A1: CurrencyId | B1: Code | C1: Country | D1: CurrencyName
A2: 1 | B2: AED | C2: United Arab Emirates | D2: Dirhams
A3: 2 | B3: AUD | C3: Australia | D3: Dollars
A4: 3 | B4: EGP | C4: Egypt | D4: Pounds
A5: 4 | B5: GBP | C5: United Kingdom | D5: Pounds
A6: 5 | B6: INR | C6: India | D6: Rupees
A7: 6 | B7: KWD | C7: Kuwait | D7: Dinars
A8: 7 | B8: PKR | C8: Pakistan | D8: Rupees
A9: 8 | B9: QAR | C9: Qatar | D9: Rials
A10: 9 | B10: SAR | C10: Saudi Arabia | D10: Riyals
A11: 10 | B11: USD | C11: United States of America | D11: Dollars
A12: 11 | B12: TRY | C12: Turkey | D12: Lira

Sheet dimcurrency
C2: Tables | D2: Currency
C5: ColumnsNeeded | D5: If name is blank, retain the original column name
C7: Table | D7: Column | E7: Logic | F7: Name
C8: Currency | D8: CurrencyId
C9: Currency | D9: Code | F9: CurrencyCode
C10: Currency | D10: LastProcessedChange_DateTime
C11: Currency | D11: DataLakeModified_DateTime | E11: ConvertToCST
C12: Currency | D12: Country
C13: Currency | D13: CurrencyName
C14: Currency | D14: RecordId | F14: CurrencyRecordId

Sheet dimdate
E1: JoinKey
B2: Tables | C2: FiscalPeriod | E2: FiscalStartDate
C3: Datetable(to be created in databricks with below columns) | E3: Date
B5: ColumnsNeeded | C5: If name is blank, retain the original column name
B7: Table | C7: Column | D7: Logic | E7: Name | F7: Comments
B8: Datetable | C8: Date | F8: Generate Dates in range 2018-01-01 to 2025-12-31
B9: Datetable | C9: DateId | D9: Convert to Int | F9: Ex: 2018-01-01 should be returned as 2010101 in int format, this will be the primary key column
B10: Datetable | C10: Year | F10: Integer
B11: Datetable | C11: Month | F11: Integer
B12: Datetable | C12: MonthName | F12: String ex: Jan, Feb, Mar…
B13: Datetable | C13: Day | F13: Integer
B14: Datetable | C14: DayName | F14: String ex: Mon, Tue
B15: Datetable | C15: Quarter | F15: Integer
B16: FiscalPeriod | C16: FISCALPERIODNAME
B17: FiscalPeriod | C17: FiscalStartDate
B18: FiscalPeriod | C18: FiscalEndDate
B19: FiscalPeriod | C19: FISCALMONTH
B20: FiscalPeriod | C20: FiscalYearStart
B21: FiscalPeriod | C21: FiscalYearEnd
B22: FiscalPeriod | C22: QUARTERACTUAL
B23: FiscalPeriod | C23: FiscalQuarterStart
B24: FiscalPeriod | C24: FiscalQuarterEnd
B25: FiscalPeriod | C25: FiscalYear | F25: Concat "FY" & FiscalYear column

Sheet Sheet2
